{ "URDMEModel" : "0ab88f92-eeb9-11e4-9550-fa163e909903", "windows_size": 40, "data_Pf": [  { "start_pos": 0, "stop_pos": 40,  "max": 1.000000, "min": 1.000000, "median": 1.000000, "avg": 1.000000, "mean": 1.000000, "std": 0.000000 } , { "start_pos": 40, "stop_pos": 80,  "max": 1.000000, "min": 0.000000, "median": 0.000000, "avg": 0.300000, "mean": 0.300000, "std": 0.458258 } , { "start_pos": 80, "stop_pos": 120,  "max": 0.000000, "min": 0.000000, "median": 0.000000, "avg": 0.000000, "mean": 0.000000, "std": 0.000000 } , { "start_pos": 120, "stop_pos": 160,  "max": 0.000000, "min": 0.000000, "median": 0.000000, "avg": 0.000000, "mean": 0.000000, "std": 0.000000 } , { "start_pos": 160, "stop_pos": 200,  "max": 0.000000, "min": 0.000000, "median": 0.000000, "avg": 0.000000, "mean": 0.000000, "std": 0.000000 } , { "start_pos": 200, "stop_pos": 240,  "max": 0.000000, "min": 0.000000, "median": 0.000000, "avg": 0.000000, "mean": 0.000000, "std": 0.000000 } , { "start_pos": 240, "stop_pos": 280,  "max": 0.000000, "min": 0.000000, "median": 0.000000, "avg": 0.000000, "mean": 0.000000, "std": 0.000000 } , { "start_pos": 280, "stop_pos": 320,  "max": 0.000000, "min": 0.000000, "median": 0.000000, "avg": 0.000000, "mean": 0.000000, "std": 0.000000 } , { "start_pos": 320, "stop_pos": 360,  "max": 0.000000, "min": 0.000000, "median": 0.000000, "avg": 0.000000, "mean": 0.000000, "std": 0.000000 } , { "start_pos": 360, "stop_pos": 400,  "max": 0.000000, "min": 0.000000, "median": 0.000000, "avg": 0.000000, "mean": 0.000000, "std": 0.000000 } , { "start_pos": 400, "stop_pos": 440,  "max": 0.000000, "min": 0.000000, "median": 0.000000, "avg": 0.000000, "mean": 0.000000, "std": 0.000000 } , { "start_pos": 440, "stop_pos": 480,  "max": 0.000000, "min": 0.000000, "median": 0.000000, "avg": 0.000000, "mean": 0.000000, "std": 0.000000 } , { "start_pos": 480, "stop_pos": 520,  "max": 0.000000, "min": 0.000000, "median": 0.000000, "avg": 0.000000, "mean": 0.000000, "std": 0.000000 } , { "start_pos": 520, "stop_pos": 560,  "max": 0.000000, "min": 0.000000, "median": 0.000000, "avg": 0.000000, "mean": 0.000000, "std": 0.000000 } , { "start_pos": 560, "stop_pos": 600,  "max": 0.000000, "min": 0.000000, "median": 0.000000, "avg": 0.000000, "mean": 0.000000, "std": 0.000000 } , { "start_pos": 600, "stop_pos": 640,  "max": 0.000000, "min": 0.000000, "median": 0.000000, "avg": 0.000000, "mean": 0.000000, "std": 0.000000 } , { "start_pos": 640, "stop_pos": 680,  "max": 0.000000, "min": 0.000000, "median": 0.000000, "avg": 0.000000, "mean": 0.000000, "std": 0.000000 } , { "start_pos": 680, "stop_pos": 720,  "max": 0.000000, "min": 0.000000, "median": 0.000000, "avg": 0.000000, "mean": 0.000000, "std": 0.000000 } , { "start_pos": 720, "stop_pos": 760,  "max": 0.000000, "min": 0.000000, "median": 0.000000, "avg": 0.000000, "mean": 0.000000, "std": 0.000000 } , { "start_pos": 760, "stop_pos": 800,  "max": 0.000000, "min": 0.000000, "median": 0.000000, "avg": 0.000000, "mean": 0.000000, "std": 0.000000 } , { "start_pos": 800, "stop_pos": 840,  "max": 0.000000, "min": 0.000000, "median": 0.000000, "avg": 0.000000, "mean": 0.000000, "std": 0.000000 } , { "start_pos": 840, "stop_pos": 880,  "max": 0.000000, "min": 0.000000, "median": 0.000000, "avg": 0.000000, "mean": 0.000000, "std": 0.000000 } , { "start_pos": 880, "stop_pos": 920,  "max": 0.000000, "min": 0.000000, "median": 0.000000, "avg": 0.000000, "mean": 0.000000, "std": 0.000000 } , { "start_pos": 920, "stop_pos": 960,  "max": 0.000000, "min": 0.000000, "median": 0.000000, "avg": 0.000000, "mean": 0.000000, "std": 0.000000 } , { "start_pos": 960, "stop_pos": 1000,  "max": 0.000000, "min": 0.000000, "median": 0.000000, "avg": 0.000000, "mean": 0.000000, "std": 0.000000 } , { "start_pos": 1000, "stop_pos": 1040,  "max": 0.000000, "min": 0.000000, "median": 0.000000, "avg": 0.000000, "mean": 0.000000, "std": 0.000000 } , { "start_pos": 1040, "stop_pos": 1080,  "max": 0.000000, "min": 0.000000, "median": 0.000000, "avg": 0.000000, "mean": 0.000000, "std": 0.000000 } , { "start_pos": 1080, "stop_pos": 1120,  "max": 0.000000, "min": 0.000000, "median": 0.000000, "avg": 0.000000, "mean": 0.000000, "std": 0.000000 } , { "start_pos": 1120, "stop_pos": 1160,  "max": 0.000000, "min": 0.000000, "median": 0.000000, "avg": 0.000000, "mean": 0.000000, "std": 0.000000 } , { "start_pos": 1160, "stop_pos": 1200,  "max": 0.000000, "min": 0.000000, "median": 0.000000, "avg": 0.000000, "mean": 0.000000, "std": 0.000000 } , { "start_pos": 1200, "stop_pos": 1240,  "max": 0.000000, "min": 0.000000, "median": 0.000000, "avg": 0.000000, "mean": 0.000000, "std": 0.000000 } , { "start_pos": 1240, "stop_pos": 1280,  "max": 0.000000, "min": 0.000000, "median": 0.000000, "avg": 0.000000, "mean": 0.000000, "std": 0.000000 } , { "start_pos": 1280, "stop_pos": 1320,  "max": 0.000000, "min": 0.000000, "median": 0.000000, "avg": 0.000000, "mean": 0.000000, "std": 0.000000 } , { "start_pos": 1320, "stop_pos": 1360,  "max": 0.000000, "min": 0.000000, "median": 0.000000, "avg": 0.000000, "mean": 0.000000, "std": 0.000000 } , { "start_pos": 1360, "stop_pos": 1400,  "max": 0.000000, "min": 0.000000, "median": 0.000000, "avg": 0.000000, "mean": 0.000000, "std": 0.000000 } , { "start_pos": 1400, "stop_pos": 1440,  "max": 0.000000, "min": 0.000000, "median": 0.000000, "avg": 0.000000, "mean": 0.000000, "std": 0.000000 } , { "start_pos": 1440, "stop_pos": 1480,  "max": 0.000000, "min": 0.000000, "median": 0.000000, "avg": 0.000000, "mean": 0.000000, "std": 0.000000 } , { "start_pos": 1480, "stop_pos": 1520,  "max": 0.000000, "min": 0.000000, "median": 0.000000, "avg": 0.000000, "mean": 0.000000, "std": 0.000000 } , { "start_pos": 1520, "stop_pos": 1560,  "max": 0.000000, "min": 0.000000, "median": 0.000000, "avg": 0.000000, "mean": 0.000000, "std": 0.000000 } , { "start_pos": 1560, "stop_pos": 1600,  "max": 0.000000, "min": 0.000000, "median": 0.000000, "avg": 0.000000, "mean": 0.000000, "std": 0.000000 } , { "start_pos": 1600, "stop_pos": 1640,  "max": 0.000000, "min": 0.000000, "median": 0.000000, "avg": 0.000000, "mean": 0.000000, "std": 0.000000 } , { "start_pos": 1640, "stop_pos": 1680,  "max": 0.000000, "min": 0.000000, "median": 0.000000, "avg": 0.000000, "mean": 0.000000, "std": 0.000000 } , { "start_pos": 1680, "stop_pos": 1720,  "max": 0.000000, "min": 0.000000, "median": 0.000000, "avg": 0.000000, "mean": 0.000000, "std": 0.000000 } , { "start_pos": 1720, "stop_pos": 1760,  "max": 0.000000, "min": 0.000000, "median": 0.000000, "avg": 0.000000, "mean": 0.000000, "std": 0.000000 } , { "start_pos": 1760, "stop_pos": 1800,  "max": 0.000000, "min": 0.000000, "median": 0.000000, "avg": 0.000000, "mean": 0.000000, "std": 0.000000 } , { "start_pos": 1800, "stop_pos": 1840,  "max": 0.000000, "min": 0.000000, "median": 0.000000, "avg": 0.000000, "mean": 0.000000, "std": 0.000000 } , { "start_pos": 1840, "stop_pos": 1880,  "max": 0.000000, "min": 0.000000, "median": 0.000000, "avg": 0.000000, "mean": 0.000000, "std": 0.000000 } , { "start_pos": 1880, "stop_pos": 1920,  "max": 0.000000, "min": 0.000000, "median": 0.000000, "avg": 0.000000, "mean": 0.000000, "std": 0.000000 } , { "start_pos": 1920, "stop_pos": 1960,  "max": 0.000000, "min": 0.000000, "median": 0.000000, "avg": 0.000000, "mean": 0.000000, "std": 0.000000 } , { "start_pos": 1960, "stop_pos": 2000,  "max": 0.000000, "min": 0.000000, "median": 0.000000, "avg": 0.000000, "mean": 0.000000, "std": 0.000000 } , { "start_pos": 2000, "stop_pos": 2040,  "max": 0.000000, "min": 0.000000, "median": 0.000000, "avg": 0.000000, "mean": 0.000000, "std": 0.000000 } , { "start_pos": 2040, "stop_pos": 2080,  "max": 0.000000, "min": 0.000000, "median": 0.000000, "avg": 0.000000, "mean": 0.000000, "std": 0.000000 } , { "start_pos": 2080, "stop_pos": 2120,  "max": 0.000000, "min": 0.000000, "median": 0.000000, "avg": 0.000000, "mean": 0.000000, "std": 0.000000 } , { "start_pos": 2120, "stop_pos": 2160,  "max": 0.000000, "min": 0.000000, "median": 0.000000, "avg": 0.000000, "mean": 0.000000, "std": 0.000000 } , { "start_pos": 2160, "stop_pos": 2200,  "max": 0.000000, "min": 0.000000, "median": 0.000000, "avg": 0.000000, "mean": 0.000000, "std": 0.000000 } , { "start_pos": 2200, "stop_pos": 2240,  "max": 0.000000, "min": 0.000000, "median": 0.000000, "avg": 0.000000, "mean": 0.000000, "std": 0.000000 } , { "start_pos": 2240, "stop_pos": 2280,  "max": 0.000000, "min": 0.000000, "median": 0.000000, "avg": 0.000000, "mean": 0.000000, "std": 0.000000 } , { "start_pos": 2280, "stop_pos": 2320,  "max": 0.000000, "min": 0.000000, "median": 0.000000, "avg": 0.000000, "mean": 0.000000, "std": 0.000000 } , { "start_pos": 2320, "stop_pos": 2360,  "max": 0.000000, "min": 0.000000, "median": 0.000000, "avg": 0.000000, "mean": 0.000000, "std": 0.000000 } , { "start_pos": 2360, "stop_pos": 2400,  "max": 0.000000, "min": 0.000000, "median": 0.000000, "avg": 0.000000, "mean": 0.000000, "std": 0.000000 } , { "start_pos": 2400, "stop_pos": 2440,  "max": 0.000000, "min": 0.000000, "median": 0.000000, "avg": 0.000000, "mean": 0.000000, "std": 0.000000 } , { "start_pos": 2440, "stop_pos": 2480,  "max": 0.000000, "min": 0.000000, "median": 0.000000, "avg": 0.000000, "mean": 0.000000, "std": 0.000000 } , { "start_pos": 2480, "stop_pos": 2520,  "max": 0.000000, "min": 0.000000, "median": 0.000000, "avg": 0.000000, "mean": 0.000000, "std": 0.000000 } , { "start_pos": 2520, "stop_pos": 2560,  "max": 0.000000, "min": 0.000000, "median": 0.000000, "avg": 0.000000, "mean": 0.000000, "std": 0.000000 } , { "start_pos": 2560, "stop_pos": 2600,  "max": 0.000000, "min": 0.000000, "median": 0.000000, "avg": 0.000000, "mean": 0.000000, "std": 0.000000 } , { "start_pos": 2600, "stop_pos": 2640,  "max": 0.000000, "min": 0.000000, "median": 0.000000, "avg": 0.000000, "mean": 0.000000, "std": 0.000000 } , { "start_pos": 2640, "stop_pos": 2680,  "max": 0.000000, "min": 0.000000, "median": 0.000000, "avg": 0.000000, "mean": 0.000000, "std": 0.000000 } , { "start_pos": 2680, "stop_pos": 2720,  "max": 0.000000, "min": 0.000000, "median": 0.000000, "avg": 0.000000, "mean": 0.000000, "std": 0.000000 } , { "start_pos": 2720, "stop_pos": 2760,  "max": 0.000000, "min": 0.000000, "median": 0.000000, "avg": 0.000000, "mean": 0.000000, "std": 0.000000 } , { "start_pos": 2760, "stop_pos": 2800,  "max": 0.000000, "min": 0.000000, "median": 0.000000, "avg": 0.000000, "mean": 0.000000, "std": 0.000000 } , { "start_pos": 2800, "stop_pos": 2840,  "max": 0.000000, "min": 0.000000, "median": 0.000000, "avg": 0.000000, "mean": 0.000000, "std": 0.000000 } , { "start_pos": 2840, "stop_pos": 2880,  "max": 0.000000, "min": 0.000000, "median": 0.000000, "avg": 0.000000, "mean": 0.000000, "std": 0.000000 } , { "start_pos": 2880, "stop_pos": 2920,  "max": 0.000000, "min": 0.000000, "median": 0.000000, "avg": 0.000000, "mean": 0.000000, "std": 0.000000 } , { "start_pos": 2920, "stop_pos": 2960,  "max": 0.000000, "min": 0.000000, "median": 0.000000, "avg": 0.000000, "mean": 0.000000, "std": 0.000000 } , { "start_pos": 2960, "stop_pos": 3000,  "max": 0.000000, "min": 0.000000, "median": 0.000000, "avg": 0.000000, "mean": 0.000000, "std": 0.000000 } , { "start_pos": 3000, "stop_pos": 3040,  "max": 0.000000, "min": 0.000000, "median": 0.000000, "avg": 0.000000, "mean": 0.000000, "std": 0.000000 } , { "start_pos": 3040, "stop_pos": 3080,  "max": 0.000000, "min": 0.000000, "median": 0.000000, "avg": 0.000000, "mean": 0.000000, "std": 0.000000 } , { "start_pos": 3080, "stop_pos": 3120,  "max": 0.000000, "min": 0.000000, "median": 0.000000, "avg": 0.000000, "mean": 0.000000, "std": 0.000000 } , { "start_pos": 3120, "stop_pos": 3160,  "max": 0.000000, "min": 0.000000, "median": 0.000000, "avg": 0.000000, "mean": 0.000000, "std": 0.000000 } , { "start_pos": 3160, "stop_pos": 3200,  "max": 0.000000, "min": 0.000000, "median": 0.000000, "avg": 0.000000, "mean": 0.000000, "std": 0.000000 } , { "start_pos": 3200, "stop_pos": 3240,  "max": 0.000000, "min": 0.000000, "median": 0.000000, "avg": 0.000000, "mean": 0.000000, "std": 0.000000 } , { "start_pos": 3240, "stop_pos": 3280,  "max": 0.000000, "min": 0.000000, "median": 0.000000, "avg": 0.000000, "mean": 0.000000, "std": 0.000000 } , { "start_pos": 3280, "stop_pos": 3320,  "max": 0.000000, "min": 0.000000, "median": 0.000000, "avg": 0.000000, "mean": 0.000000, "std": 0.000000 } , { "start_pos": 3320, "stop_pos": 3360,  "max": 0.000000, "min": 0.000000, "median": 0.000000, "avg": 0.000000, "mean": 0.000000, "std": 0.000000 } , { "start_pos": 3360, "stop_pos": 3400,  "max": 0.000000, "min": 0.000000, "median": 0.000000, "avg": 0.000000, "mean": 0.000000, "std": 0.000000 } , { "start_pos": 3400, "stop_pos": 3440,  "max": 0.000000, "min": 0.000000, "median": 0.000000, "avg": 0.000000, "mean": 0.000000, "std": 0.000000 } , { "start_pos": 3440, "stop_pos": 3480,  "max": 0.000000, "min": 0.000000, "median": 0.000000, "avg": 0.000000, "mean": 0.000000, "std": 0.000000 } , { "start_pos": 3480, "stop_pos": 3520,  "max": 0.000000, "min": 0.000000, "median": 0.000000, "avg": 0.000000, "mean": 0.000000, "std": 0.000000 } , { "start_pos": 3520, "stop_pos": 3560,  "max": 0.000000, "min": 0.000000, "median": 0.000000, "avg": 0.000000, "mean": 0.000000, "std": 0.000000 } , { "start_pos": 3560, "stop_pos": 3600,  "max": 0.000000, "min": 0.000000, "median": 0.000000, "avg": 0.000000, "mean": 0.000000, "std": 0.000000 } , { "start_pos": 3600, "stop_pos": 3640,  "max": 0.000000, "min": 0.000000, "median": 0.000000, "avg": 0.000000, "mean": 0.000000, "std": 0.000000 } , { "start_pos": 3640, "stop_pos": 3680,  "max": 0.000000, "min": 0.000000, "median": 0.000000, "avg": 0.000000, "mean": 0.000000, "std": 0.000000 } , { "start_pos": 3680, "stop_pos": 3720,  "max": 0.000000, "min": 0.000000, "median": 0.000000, "avg": 0.000000, "mean": 0.000000, "std": 0.000000 } , { "start_pos": 3720, "stop_pos": 3760,  "max": 0.000000, "min": 0.000000, "median": 0.000000, "avg": 0.000000, "mean": 0.000000, "std": 0.000000 } , { "start_pos": 3760, "stop_pos": 3800,  "max": 0.000000, "min": 0.000000, "median": 0.000000, "avg": 0.000000, "mean": 0.000000, "std": 0.000000 } , { "start_pos": 3800, "stop_pos": 3840,  "max": 0.000000, "min": 0.000000, "median": 0.000000, "avg": 0.000000, "mean": 0.000000, "std": 0.000000 } , { "start_pos": 3840, "stop_pos": 3880,  "max": 0.000000, "min": 0.000000, "median": 0.000000, "avg": 0.000000, "mean": 0.000000, "std": 0.000000 } , { "start_pos": 3880, "stop_pos": 3920,  "max": 0.000000, "min": 0.000000, "median": 0.000000, "avg": 0.000000, "mean": 0.000000, "std": 0.000000 } , { "start_pos": 3920, "stop_pos": 3960,  "max": 0.000000, "min": 0.000000, "median": 0.000000, "avg": 0.000000, "mean": 0.000000, "std": 0.000000 } , { "start_pos": 3960, "stop_pos": 4000,  "max": 0.000000, "min": 0.000000, "median": 0.000000, "avg": 0.000000, "mean": 0.000000, "std": 0.000000 } ], "data_Po": [  { "start_pos": 0, "stop_pos": 40,  "max": 0.000000, "min": 0.000000, "median": 0.000000, "avg": 0.000000, "mean": 0.000000, "std": 0.000000 } , { "start_pos": 40, "stop_pos": 80,  "max": 1.000000, "min": 0.000000, "median": 1.000000, "avg": 0.700000, "mean": 0.700000, "std": 0.458258 } , { "start_pos": 80, "stop_pos": 120,  "max": 1.000000, "min": 1.000000, "median": 1.000000, "avg": 1.000000, "mean": 1.000000, "std": 0.000000 } , { "start_pos": 120, "stop_pos": 160,  "max": 1.000000, "min": 1.000000, "median": 1.000000, "avg": 1.000000, "mean": 1.000000, "std": 0.000000 } , { "start_pos": 160, "stop_pos": 200,  "max": 1.000000, "min": 1.000000, "median": 1.000000, "avg": 1.000000, "mean": 1.000000, "std": 0.000000 } , { "start_pos": 200, "stop_pos": 240,  "max": 1.000000, "min": 1.000000, "median": 1.000000, "avg": 1.000000, "mean": 1.000000, "std": 0.000000 } , { "start_pos": 240, "stop_pos": 280,  "max": 1.000000, "min": 1.000000, "median": 1.000000, "avg": 1.000000, "mean": 1.000000, "std": 0.000000 } , { "start_pos": 280, "stop_pos": 320,  "max": 1.000000, "min": 1.000000, "median": 1.000000, "avg": 1.000000, "mean": 1.000000, "std": 0.000000 } , { "start_pos": 320, "stop_pos": 360,  "max": 1.000000, "min": 1.000000, "median": 1.000000, "avg": 1.000000, "mean": 1.000000, "std": 0.000000 } , { "start_pos": 360, "stop_pos": 400,  "max": 1.000000, "min": 1.000000, "median": 1.000000, "avg": 1.000000, "mean": 1.000000, "std": 0.000000 } , { "start_pos": 400, "stop_pos": 440,  "max": 1.000000, "min": 1.000000, "median": 1.000000, "avg": 1.000000, "mean": 1.000000, "std": 0.000000 } , { "start_pos": 440, "stop_pos": 480,  "max": 1.000000, "min": 1.000000, "median": 1.000000, "avg": 1.000000, "mean": 1.000000, "std": 0.000000 } , { "start_pos": 480, "stop_pos": 520,  "max": 1.000000, "min": 1.000000, "median": 1.000000, "avg": 1.000000, "mean": 1.000000, "std": 0.000000 } , { "start_pos": 520, "stop_pos": 560,  "max": 1.000000, "min": 1.000000, "median": 1.000000, "avg": 1.000000, "mean": 1.000000, "std": 0.000000 } , { "start_pos": 560, "stop_pos": 600,  "max": 1.000000, "min": 1.000000, "median": 1.000000, "avg": 1.000000, "mean": 1.000000, "std": 0.000000 } , { "start_pos": 600, "stop_pos": 640,  "max": 1.000000, "min": 1.000000, "median": 1.000000, "avg": 1.000000, "mean": 1.000000, "std": 0.000000 } , { "start_pos": 640, "stop_pos": 680,  "max": 1.000000, "min": 1.000000, "median": 1.000000, "avg": 1.000000, "mean": 1.000000, "std": 0.000000 } , { "start_pos": 680, "stop_pos": 720,  "max": 1.000000, "min": 1.000000, "median": 1.000000, "avg": 1.000000, "mean": 1.000000, "std": 0.000000 } , { "start_pos": 720, "stop_pos": 760,  "max": 1.000000, "min": 1.000000, "median": 1.000000, "avg": 1.000000, "mean": 1.000000, "std": 0.000000 } , { "start_pos": 760, "stop_pos": 800,  "max": 1.000000, "min": 1.000000, "median": 1.000000, "avg": 1.000000, "mean": 1.000000, "std": 0.000000 } , { "start_pos": 800, "stop_pos": 840,  "max": 1.000000, "min": 1.000000, "median": 1.000000, "avg": 1.000000, "mean": 1.000000, "std": 0.000000 } , { "start_pos": 840, "stop_pos": 880,  "max": 1.000000, "min": 1.000000, "median": 1.000000, "avg": 1.000000, "mean": 1.000000, "std": 0.000000 } , { "start_pos": 880, "stop_pos": 920,  "max": 1.000000, "min": 1.000000, "median": 1.000000, "avg": 1.000000, "mean": 1.000000, "std": 0.000000 } , { "start_pos": 920, "stop_pos": 960,  "max": 1.000000, "min": 1.000000, "median": 1.000000, "avg": 1.000000, "mean": 1.000000, "std": 0.000000 } , { "start_pos": 960, "stop_pos": 1000,  "max": 1.000000, "min": 1.000000, "median": 1.000000, "avg": 1.000000, "mean": 1.000000, "std": 0.000000 } , { "start_pos": 1000, "stop_pos": 1040,  "max": 1.000000, "min": 1.000000, "median": 1.000000, "avg": 1.000000, "mean": 1.000000, "std": 0.000000 } , { "start_pos": 1040, "stop_pos": 1080,  "max": 1.000000, "min": 1.000000, "median": 1.000000, "avg": 1.000000, "mean": 1.000000, "std": 0.000000 } , { "start_pos": 1080, "stop_pos": 1120,  "max": 1.000000, "min": 1.000000, "median": 1.000000, "avg": 1.000000, "mean": 1.000000, "std": 0.000000 } , { "start_pos": 1120, "stop_pos": 1160,  "max": 1.000000, "min": 1.000000, "median": 1.000000, "avg": 1.000000, "mean": 1.000000, "std": 0.000000 } , { "start_pos": 1160, "stop_pos": 1200,  "max": 1.000000, "min": 1.000000, "median": 1.000000, "avg": 1.000000, "mean": 1.000000, "std": 0.000000 } , { "start_pos": 1200, "stop_pos": 1240,  "max": 1.000000, "min": 1.000000, "median": 1.000000, "avg": 1.000000, "mean": 1.000000, "std": 0.000000 } , { "start_pos": 1240, "stop_pos": 1280,  "max": 1.000000, "min": 1.000000, "median": 1.000000, "avg": 1.000000, "mean": 1.000000, "std": 0.000000 } , { "start_pos": 1280, "stop_pos": 1320,  "max": 1.000000, "min": 1.000000, "median": 1.000000, "avg": 1.000000, "mean": 1.000000, "std": 0.000000 } , { "start_pos": 1320, "stop_pos": 1360,  "max": 1.000000, "min": 1.000000, "median": 1.000000, "avg": 1.000000, "mean": 1.000000, "std": 0.000000 } , { "start_pos": 1360, "stop_pos": 1400,  "max": 1.000000, "min": 1.000000, "median": 1.000000, "avg": 1.000000, "mean": 1.000000, "std": 0.000000 } , { "start_pos": 1400, "stop_pos": 1440,  "max": 1.000000, "min": 1.000000, "median": 1.000000, "avg": 1.000000, "mean": 1.000000, "std": 0.000000 } , { "start_pos": 1440, "stop_pos": 1480,  "max": 1.000000, "min": 1.000000, "median": 1.000000, "avg": 1.000000, "mean": 1.000000, "std": 0.000000 } , { "start_pos": 1480, "stop_pos": 1520,  "max": 1.000000, "min": 1.000000, "median": 1.000000, "avg": 1.000000, "mean": 1.000000, "std": 0.000000 } , { "start_pos": 1520, "stop_pos": 1560,  "max": 1.000000, "min": 1.000000, "median": 1.000000, "avg": 1.000000, "mean": 1.000000, "std": 0.000000 } , { "start_pos": 1560, "stop_pos": 1600,  "max": 1.000000, "min": 1.000000, "median": 1.000000, "avg": 1.000000, "mean": 1.000000, "std": 0.000000 } , { "start_pos": 1600, "stop_pos": 1640,  "max": 1.000000, "min": 1.000000, "median": 1.000000, "avg": 1.000000, "mean": 1.000000, "std": 0.000000 } , { "start_pos": 1640, "stop_pos": 1680,  "max": 1.000000, "min": 1.000000, "median": 1.000000, "avg": 1.000000, "mean": 1.000000, "std": 0.000000 } , { "start_pos": 1680, "stop_pos": 1720,  "max": 1.000000, "min": 1.000000, "median": 1.000000, "avg": 1.000000, "mean": 1.000000, "std": 0.000000 } , { "start_pos": 1720, "stop_pos": 1760,  "max": 1.000000, "min": 1.000000, "median": 1.000000, "avg": 1.000000, "mean": 1.000000, "std": 0.000000 } , { "start_pos": 1760, "stop_pos": 1800,  "max": 1.000000, "min": 1.000000, "median": 1.000000, "avg": 1.000000, "mean": 1.000000, "std": 0.000000 } , { "start_pos": 1800, "stop_pos": 1840,  "max": 1.000000, "min": 1.000000, "median": 1.000000, "avg": 1.000000, "mean": 1.000000, "std": 0.000000 } , { "start_pos": 1840, "stop_pos": 1880,  "max": 1.000000, "min": 1.000000, "median": 1.000000, "avg": 1.000000, "mean": 1.000000, "std": 0.000000 } , { "start_pos": 1880, "stop_pos": 1920,  "max": 1.000000, "min": 1.000000, "median": 1.000000, "avg": 1.000000, "mean": 1.000000, "std": 0.000000 } , { "start_pos": 1920, "stop_pos": 1960,  "max": 1.000000, "min": 1.000000, "median": 1.000000, "avg": 1.000000, "mean": 1.000000, "std": 0.000000 } , { "start_pos": 1960, "stop_pos": 2000,  "max": 1.000000, "min": 1.000000, "median": 1.000000, "avg": 1.000000, "mean": 1.000000, "std": 0.000000 } , { "start_pos": 2000, "stop_pos": 2040,  "max": 1.000000, "min": 1.000000, "median": 1.000000, "avg": 1.000000, "mean": 1.000000, "std": 0.000000 } , { "start_pos": 2040, "stop_pos": 2080,  "max": 1.000000, "min": 1.000000, "median": 1.000000, "avg": 1.000000, "mean": 1.000000, "std": 0.000000 } , { "start_pos": 2080, "stop_pos": 2120,  "max": 1.000000, "min": 1.000000, "median": 1.000000, "avg": 1.000000, "mean": 1.000000, "std": 0.000000 } , { "start_pos": 2120, "stop_pos": 2160,  "max": 1.000000, "min": 1.000000, "median": 1.000000, "avg": 1.000000, "mean": 1.000000, "std": 0.000000 } , { "start_pos": 2160, "stop_pos": 2200,  "max": 1.000000, "min": 1.000000, "median": 1.000000, "avg": 1.000000, "mean": 1.000000, "std": 0.000000 } , { "start_pos": 2200, "stop_pos": 2240,  "max": 1.000000, "min": 1.000000, "median": 1.000000, "avg": 1.000000, "mean": 1.000000, "std": 0.000000 } , { "start_pos": 2240, "stop_pos": 2280,  "max": 1.000000, "min": 1.000000, "median": 1.000000, "avg": 1.000000, "mean": 1.000000, "std": 0.000000 } , { "start_pos": 2280, "stop_pos": 2320,  "max": 1.000000, "min": 1.000000, "median": 1.000000, "avg": 1.000000, "mean": 1.000000, "std": 0.000000 } , { "start_pos": 2320, "stop_pos": 2360,  "max": 1.000000, "min": 1.000000, "median": 1.000000, "avg": 1.000000, "mean": 1.000000, "std": 0.000000 } , { "start_pos": 2360, "stop_pos": 2400,  "max": 1.000000, "min": 1.000000, "median": 1.000000, "avg": 1.000000, "mean": 1.000000, "std": 0.000000 } , { "start_pos": 2400, "stop_pos": 2440,  "max": 1.000000, "min": 1.000000, "median": 1.000000, "avg": 1.000000, "mean": 1.000000, "std": 0.000000 } , { "start_pos": 2440, "stop_pos": 2480,  "max": 1.000000, "min": 1.000000, "median": 1.000000, "avg": 1.000000, "mean": 1.000000, "std": 0.000000 } , { "start_pos": 2480, "stop_pos": 2520,  "max": 1.000000, "min": 1.000000, "median": 1.000000, "avg": 1.000000, "mean": 1.000000, "std": 0.000000 } , { "start_pos": 2520, "stop_pos": 2560,  "max": 1.000000, "min": 1.000000, "median": 1.000000, "avg": 1.000000, "mean": 1.000000, "std": 0.000000 } , { "start_pos": 2560, "stop_pos": 2600,  "max": 1.000000, "min": 1.000000, "median": 1.000000, "avg": 1.000000, "mean": 1.000000, "std": 0.000000 } , { "start_pos": 2600, "stop_pos": 2640,  "max": 1.000000, "min": 1.000000, "median": 1.000000, "avg": 1.000000, "mean": 1.000000, "std": 0.000000 } , { "start_pos": 2640, "stop_pos": 2680,  "max": 1.000000, "min": 1.000000, "median": 1.000000, "avg": 1.000000, "mean": 1.000000, "std": 0.000000 } , { "start_pos": 2680, "stop_pos": 2720,  "max": 1.000000, "min": 1.000000, "median": 1.000000, "avg": 1.000000, "mean": 1.000000, "std": 0.000000 } , { "start_pos": 2720, "stop_pos": 2760,  "max": 1.000000, "min": 1.000000, "median": 1.000000, "avg": 1.000000, "mean": 1.000000, "std": 0.000000 } , { "start_pos": 2760, "stop_pos": 2800,  "max": 1.000000, "min": 1.000000, "median": 1.000000, "avg": 1.000000, "mean": 1.000000, "std": 0.000000 } , { "start_pos": 2800, "stop_pos": 2840,  "max": 1.000000, "min": 1.000000, "median": 1.000000, "avg": 1.000000, "mean": 1.000000, "std": 0.000000 } , { "start_pos": 2840, "stop_pos": 2880,  "max": 1.000000, "min": 1.000000, "median": 1.000000, "avg": 1.000000, "mean": 1.000000, "std": 0.000000 } , { "start_pos": 2880, "stop_pos": 2920,  "max": 1.000000, "min": 1.000000, "median": 1.000000, "avg": 1.000000, "mean": 1.000000, "std": 0.000000 } , { "start_pos": 2920, "stop_pos": 2960,  "max": 1.000000, "min": 1.000000, "median": 1.000000, "avg": 1.000000, "mean": 1.000000, "std": 0.000000 } , { "start_pos": 2960, "stop_pos": 3000,  "max": 1.000000, "min": 1.000000, "median": 1.000000, "avg": 1.000000, "mean": 1.000000, "std": 0.000000 } , { "start_pos": 3000, "stop_pos": 3040,  "max": 1.000000, "min": 1.000000, "median": 1.000000, "avg": 1.000000, "mean": 1.000000, "std": 0.000000 } , { "start_pos": 3040, "stop_pos": 3080,  "max": 1.000000, "min": 1.000000, "median": 1.000000, "avg": 1.000000, "mean": 1.000000, "std": 0.000000 } , { "start_pos": 3080, "stop_pos": 3120,  "max": 1.000000, "min": 1.000000, "median": 1.000000, "avg": 1.000000, "mean": 1.000000, "std": 0.000000 } , { "start_pos": 3120, "stop_pos": 3160,  "max": 1.000000, "min": 1.000000, "median": 1.000000, "avg": 1.000000, "mean": 1.000000, "std": 0.000000 } , { "start_pos": 3160, "stop_pos": 3200,  "max": 1.000000, "min": 1.000000, "median": 1.000000, "avg": 1.000000, "mean": 1.000000, "std": 0.000000 } , { "start_pos": 3200, "stop_pos": 3240,  "max": 1.000000, "min": 1.000000, "median": 1.000000, "avg": 1.000000, "mean": 1.000000, "std": 0.000000 } , { "start_pos": 3240, "stop_pos": 3280,  "max": 1.000000, "min": 1.000000, "median": 1.000000, "avg": 1.000000, "mean": 1.000000, "std": 0.000000 } , { "start_pos": 3280, "stop_pos": 3320,  "max": 1.000000, "min": 1.000000, "median": 1.000000, "avg": 1.000000, "mean": 1.000000, "std": 0.000000 } , { "start_pos": 3320, "stop_pos": 3360,  "max": 1.000000, "min": 1.000000, "median": 1.000000, "avg": 1.000000, "mean": 1.000000, "std": 0.000000 } , { "start_pos": 3360, "stop_pos": 3400,  "max": 1.000000, "min": 1.000000, "median": 1.000000, "avg": 1.000000, "mean": 1.000000, "std": 0.000000 } , { "start_pos": 3400, "stop_pos": 3440,  "max": 1.000000, "min": 1.000000, "median": 1.000000, "avg": 1.000000, "mean": 1.000000, "std": 0.000000 } , { "start_pos": 3440, "stop_pos": 3480,  "max": 1.000000, "min": 1.000000, "median": 1.000000, "avg": 1.000000, "mean": 1.000000, "std": 0.000000 } , { "start_pos": 3480, "stop_pos": 3520,  "max": 1.000000, "min": 1.000000, "median": 1.000000, "avg": 1.000000, "mean": 1.000000, "std": 0.000000 } , { "start_pos": 3520, "stop_pos": 3560,  "max": 1.000000, "min": 1.000000, "median": 1.000000, "avg": 1.000000, "mean": 1.000000, "std": 0.000000 } , { "start_pos": 3560, "stop_pos": 3600,  "max": 1.000000, "min": 1.000000, "median": 1.000000, "avg": 1.000000, "mean": 1.000000, "std": 0.000000 } , { "start_pos": 3600, "stop_pos": 3640,  "max": 1.000000, "min": 1.000000, "median": 1.000000, "avg": 1.000000, "mean": 1.000000, "std": 0.000000 } , { "start_pos": 3640, "stop_pos": 3680,  "max": 1.000000, "min": 1.000000, "median": 1.000000, "avg": 1.000000, "mean": 1.000000, "std": 0.000000 } , { "start_pos": 3680, "stop_pos": 3720,  "max": 1.000000, "min": 1.000000, "median": 1.000000, "avg": 1.000000, "mean": 1.000000, "std": 0.000000 } , { "start_pos": 3720, "stop_pos": 3760,  "max": 1.000000, "min": 1.000000, "median": 1.000000, "avg": 1.000000, "mean": 1.000000, "std": 0.000000 } , { "start_pos": 3760, "stop_pos": 3800,  "max": 1.000000, "min": 1.000000, "median": 1.000000, "avg": 1.000000, "mean": 1.000000, "std": 0.000000 } , { "start_pos": 3800, "stop_pos": 3840,  "max": 1.000000, "min": 1.000000, "median": 1.000000, "avg": 1.000000, "mean": 1.000000, "std": 0.000000 } , { "start_pos": 3840, "stop_pos": 3880,  "max": 1.000000, "min": 1.000000, "median": 1.000000, "avg": 1.000000, "mean": 1.000000, "std": 0.000000 } , { "start_pos": 3880, "stop_pos": 3920,  "max": 1.000000, "min": 1.000000, "median": 1.000000, "avg": 1.000000, "mean": 1.000000, "std": 0.000000 } , { "start_pos": 3920, "stop_pos": 3960,  "max": 1.000000, "min": 1.000000, "median": 1.000000, "avg": 1.000000, "mean": 1.000000, "std": 0.000000 } , { "start_pos": 3960, "stop_pos": 4000,  "max": 1.000000, "min": 1.000000, "median": 1.000000, "avg": 1.000000, "mean": 1.000000, "std": 0.000000 } ], "data_mRNA": [  { "start_pos": 0, "stop_pos": 40,  "max": 28.000000, "min": 10.000000, "median": 18.000000, "avg": 19.125000, "mean": 19.125000, "std": 4.319650 } , { "start_pos": 40, "stop_pos": 80,  "max": 30.000000, "min": 19.000000, "median": 23.000000, "avg": 24.325000, "mean": 24.325000, "std": 3.149504 } , { "start_pos": 80, "stop_pos": 120,  "max": 19.000000, "min": 11.000000, "median": 15.000000, "avg": 14.675000, "mean": 14.675000, "std": 3.227906 } , { "start_pos": 120, "stop_pos": 160,  "max": 11.000000, "min": 5.000000, "median": 7.000000, "avg": 8.000000, "mean": 8.000000, "std": 1.870829 } , { "start_pos": 160, "stop_pos": 200,  "max": 4.000000, "min": 1.000000, "median": 2.000000, "avg": 2.075000, "mean": 2.075000, "std": 0.818153 } , { "start_pos": 200, "stop_pos": 240,  "max": 4.000000, "min": 2.000000, "median": 2.000000, "avg": 2.425000, "mean": 2.425000, "std": 0.666615 } , { "start_pos": 240, "stop_pos": 280,  "max": 5.000000, "min": 1.000000, "median": 2.000000, "avg": 2.650000, "mean": 2.650000, "std": 1.370219 } , { "start_pos": 280, "stop_pos": 320,  "max": 1.000000, "min": 0.000000, "median": 1.000000, "avg": 0.925000, "mean": 0.925000, "std": 0.263391 } , { "start_pos": 320, "stop_pos": 360,  "max": 3.000000, "min": 1.000000, "median": 1.000000, "avg": 1.550000, "mean": 1.550000, "std": 0.739932 } , { "start_pos": 360, "stop_pos": 400,  "max": 1.000000, "min": 0.000000, "median": 1.000000, "avg": 0.675000, "mean": 0.675000, "std": 0.468375 } , { "start_pos": 400, "stop_pos": 440,  "max": 1.000000, "min": 0.000000, "median": 1.000000, "avg": 0.825000, "mean": 0.825000, "std": 0.379967 } , { "start_pos": 440, "stop_pos": 480,  "max": 1.000000, "min": 1.000000, "median": 1.000000, "avg": 1.000000, "mean": 1.000000, "std": 0.000000 } , { "start_pos": 480, "stop_pos": 520,  "max": 1.000000, "min": 0.000000, "median": 0.000000, "avg": 0.075000, "mean": 0.075000, "std": 0.263391 } , { "start_pos": 520, "stop_pos": 560,  "max": 1.000000, "min": 0.000000, "median": 0.000000, "avg": 0.400000, "mean": 0.400000, "std": 0.489898 } , { "start_pos": 560, "stop_pos": 600,  "max": 1.000000, "min": 0.000000, "median": 0.000000, "avg": 0.400000, "mean": 0.400000, "std": 0.489898 } , { "start_pos": 600, "stop_pos": 640,  "max": 2.000000, "min": 0.000000, "median": 2.000000, "avg": 1.350000, "mean": 1.350000, "std": 0.823104 } , { "start_pos": 640, "stop_pos": 680,  "max": 0.000000, "min": 0.000000, "median": 0.000000, "avg": 0.000000, "mean": 0.000000, "std": 0.000000 } , { "start_pos": 680, "stop_pos": 720,  "max": 4.000000, "min": 0.000000, "median": 4.000000, "avg": 3.400000, "mean": 3.400000, "std": 1.280625 } , { "start_pos": 720, "stop_pos": 760,  "max": 4.000000, "min": 0.000000, "median": 2.000000, "avg": 2.175000, "mean": 2.175000, "std": 0.862772 } , { "start_pos": 760, "stop_pos": 800,  "max": 0.000000, "min": 0.000000, "median": 0.000000, "avg": 0.000000, "mean": 0.000000, "std": 0.000000 } , { "start_pos": 800, "stop_pos": 840,  "max": 1.000000, "min": 0.000000, "median": 0.000000, "avg": 0.300000, "mean": 0.300000, "std": 0.458258 } , { "start_pos": 840, "stop_pos": 880,  "max": 0.000000, "min": 0.000000, "median": 0.000000, "avg": 0.000000, "mean": 0.000000, "std": 0.000000 } , { "start_pos": 880, "stop_pos": 920,  "max": 1.000000, "min": 0.000000, "median": 0.000000, "avg": 0.475000, "mean": 0.475000, "std": 0.499375 } , { "start_pos": 920, "stop_pos": 960,  "max": 1.000000, "min": 0.000000, "median": 0.000000, "avg": 0.225000, "mean": 0.225000, "std": 0.417582 } , { "start_pos": 960, "stop_pos": 1000,  "max": 1.000000, "min": 0.000000, "median": 1.000000, "avg": 0.625000, "mean": 0.625000, "std": 0.484123 } , { "start_pos": 1000, "stop_pos": 1040,  "max": 1.000000, "min": 0.000000, "median": 0.000000, "avg": 0.050000, "mean": 0.050000, "std": 0.217945 } , { "start_pos": 1040, "stop_pos": 1080,  "max": 2.000000, "min": 0.000000, "median": 1.000000, "avg": 1.075000, "mean": 1.075000, "std": 0.787004 } , { "start_pos": 1080, "stop_pos": 1120,  "max": 5.000000, "min": 1.000000, "median": 1.000000, "avg": 2.125000, "mean": 2.125000, "std": 1.417524 } , { "start_pos": 1120, "stop_pos": 1160,  "max": 4.000000, "min": 1.000000, "median": 2.000000, "avg": 2.600000, "mean": 2.600000, "std": 1.260952 } , { "start_pos": 1160, "stop_pos": 1200,  "max": 3.000000, "min": 1.000000, "median": 2.000000, "avg": 2.000000, "mean": 2.000000, "std": 0.894427 } , { "start_pos": 1200, "stop_pos": 1240,  "max": 3.000000, "min": 2.000000, "median": 2.000000, "avg": 2.300000, "mean": 2.300000, "std": 0.458258 } , { "start_pos": 1240, "stop_pos": 1280,  "max": 4.000000, "min": 2.000000, "median": 3.000000, "avg": 2.825000, "mean": 2.825000, "std": 0.586835 } , { "start_pos": 1280, "stop_pos": 1320,  "max": 3.000000, "min": 2.000000, "median": 3.000000, "avg": 2.825000, "mean": 2.825000, "std": 0.379967 } , { "start_pos": 1320, "stop_pos": 1360,  "max": 3.000000, "min": 0.000000, "median": 1.000000, "avg": 1.175000, "mean": 1.175000, "std": 1.092875 } , { "start_pos": 1360, "stop_pos": 1400,  "max": 1.000000, "min": 0.000000, "median": 0.000000, "avg": 0.425000, "mean": 0.425000, "std": 0.494343 } , { "start_pos": 1400, "stop_pos": 1440,  "max": 2.000000, "min": 1.000000, "median": 1.000000, "avg": 1.050000, "mean": 1.050000, "std": 0.217945 } , { "start_pos": 1440, "stop_pos": 1480,  "max": 2.000000, "min": 0.000000, "median": 1.000000, "avg": 0.725000, "mean": 0.725000, "std": 0.706665 } , { "start_pos": 1480, "stop_pos": 1520,  "max": 2.000000, "min": 0.000000, "median": 0.000000, "avg": 0.725000, "mean": 0.725000, "std": 0.921615 } , { "start_pos": 1520, "stop_pos": 1560,  "max": 4.000000, "min": 2.000000, "median": 3.000000, "avg": 3.025000, "mean": 3.025000, "std": 0.523808 } , { "start_pos": 1560, "stop_pos": 1600,  "max": 4.000000, "min": 1.000000, "median": 2.000000, "avg": 1.750000, "mean": 1.750000, "std": 0.829156 } , { "start_pos": 1600, "stop_pos": 1640,  "max": 1.000000, "min": 1.000000, "median": 1.000000, "avg": 1.000000, "mean": 1.000000, "std": 0.000000 } , { "start_pos": 1640, "stop_pos": 1680,  "max": 1.000000, "min": 1.000000, "median": 1.000000, "avg": 1.000000, "mean": 1.000000, "std": 0.000000 } , { "start_pos": 1680, "stop_pos": 1720,  "max": 2.000000, "min": 1.000000, "median": 1.000000, "avg": 1.200000, "mean": 1.200000, "std": 0.400000 } , { "start_pos": 1720, "stop_pos": 1760,  "max": 1.000000, "min": 0.000000, "median": 1.000000, "avg": 0.650000, "mean": 0.650000, "std": 0.476970 } , { "start_pos": 1760, "stop_pos": 1800,  "max": 1.000000, "min": 0.000000, "median": 0.000000, "avg": 0.150000, "mean": 0.150000, "std": 0.357071 } , { "start_pos": 1800, "stop_pos": 1840,  "max": 0.000000, "min": 0.000000, "median": 0.000000, "avg": 0.000000, "mean": 0.000000, "std": 0.000000 } , { "start_pos": 1840, "stop_pos": 1880,  "max": 1.000000, "min": 0.000000, "median": 0.000000, "avg": 0.100000, "mean": 0.100000, "std": 0.300000 } , { "start_pos": 1880, "stop_pos": 1920,  "max": 3.000000, "min": 1.000000, "median": 1.000000, "avg": 1.275000, "mean": 1.275000, "std": 0.499375 } , { "start_pos": 1920, "stop_pos": 1960,  "max": 3.000000, "min": 2.000000, "median": 2.000000, "avg": 2.050000, "mean": 2.050000, "std": 0.217945 } , { "start_pos": 1960, "stop_pos": 2000,  "max": 2.000000, "min": 1.000000, "median": 1.000000, "avg": 1.325000, "mean": 1.325000, "std": 0.468375 } , { "start_pos": 2000, "stop_pos": 2040,  "max": 2.000000, "min": 0.000000, "median": 1.000000, "avg": 0.625000, "mean": 0.625000, "std": 0.533268 } , { "start_pos": 2040, "stop_pos": 2080,  "max": 1.000000, "min": 1.000000, "median": 1.000000, "avg": 1.000000, "mean": 1.000000, "std": 0.000000 } , { "start_pos": 2080, "stop_pos": 2120,  "max": 1.000000, "min": 0.000000, "median": 1.000000, "avg": 0.675000, "mean": 0.675000, "std": 0.468375 } , { "start_pos": 2120, "stop_pos": 2160,  "max": 1.000000, "min": 0.000000, "median": 0.000000, "avg": 0.450000, "mean": 0.450000, "std": 0.497494 } , { "start_pos": 2160, "stop_pos": 2200,  "max": 4.000000, "min": 1.000000, "median": 3.000000, "avg": 2.550000, "mean": 2.550000, "std": 0.864581 } , { "start_pos": 2200, "stop_pos": 2240,  "max": 4.000000, "min": 1.000000, "median": 1.000000, "avg": 1.475000, "mean": 1.475000, "std": 0.948354 } , { "start_pos": 2240, "stop_pos": 2280,  "max": 1.000000, "min": 0.000000, "median": 1.000000, "avg": 0.625000, "mean": 0.625000, "std": 0.484123 } , { "start_pos": 2280, "stop_pos": 2320,  "max": 2.000000, "min": 1.000000, "median": 2.000000, "avg": 1.900000, "mean": 1.900000, "std": 0.300000 } , { "start_pos": 2320, "stop_pos": 2360,  "max": 2.000000, "min": 1.000000, "median": 2.000000, "avg": 1.650000, "mean": 1.650000, "std": 0.476970 } , { "start_pos": 2360, "stop_pos": 2400,  "max": 2.000000, "min": 0.000000, "median": 1.000000, "avg": 0.825000, "mean": 0.825000, "std": 0.440880 } , { "start_pos": 2400, "stop_pos": 2440,  "max": 2.000000, "min": 0.000000, "median": 0.000000, "avg": 0.375000, "mean": 0.375000, "std": 0.731010 } , { "start_pos": 2440, "stop_pos": 2480,  "max": 4.000000, "min": 2.000000, "median": 2.000000, "avg": 2.550000, "mean": 2.550000, "std": 0.630476 } , { "start_pos": 2480, "stop_pos": 2520,  "max": 3.000000, "min": 1.000000, "median": 2.000000, "avg": 2.025000, "mean": 2.025000, "std": 0.569539 } , { "start_pos": 2520, "stop_pos": 2560,  "max": 4.000000, "min": 2.000000, "median": 4.000000, "avg": 3.275000, "mean": 3.275000, "std": 0.894078 } , { "start_pos": 2560, "stop_pos": 2600,  "max": 5.000000, "min": 2.000000, "median": 3.000000, "avg": 3.325000, "mean": 3.325000, "std": 0.848160 } , { "start_pos": 2600, "stop_pos": 2640,  "max": 3.000000, "min": 1.000000, "median": 2.000000, "avg": 1.825000, "mean": 1.825000, "std": 0.586835 } , { "start_pos": 2640, "stop_pos": 2680,  "max": 2.000000, "min": 0.000000, "median": 0.000000, "avg": 0.175000, "mean": 0.175000, "std": 0.542563 } , { "start_pos": 2680, "stop_pos": 2720,  "max": 2.000000, "min": 0.000000, "median": 2.000000, "avg": 1.725000, "mean": 1.725000, "std": 0.547152 } , { "start_pos": 2720, "stop_pos": 2760,  "max": 3.000000, "min": 1.000000, "median": 2.000000, "avg": 1.850000, "mean": 1.850000, "std": 0.691014 } , { "start_pos": 2760, "stop_pos": 2800,  "max": 6.000000, "min": 3.000000, "median": 4.000000, "avg": 3.775000, "mean": 3.775000, "std": 0.790174 } , { "start_pos": 2800, "stop_pos": 2840,  "max": 5.000000, "min": 3.000000, "median": 5.000000, "avg": 4.275000, "mean": 4.275000, "std": 0.836286 } , { "start_pos": 2840, "stop_pos": 2880,  "max": 3.000000, "min": 2.000000, "median": 3.000000, "avg": 2.625000, "mean": 2.625000, "std": 0.484123 } , { "start_pos": 2880, "stop_pos": 2920,  "max": 3.000000, "min": 1.000000, "median": 1.000000, "avg": 1.375000, "mean": 1.375000, "std": 0.578252 } , { "start_pos": 2920, "stop_pos": 2960,  "max": 1.000000, "min": 1.000000, "median": 1.000000, "avg": 1.000000, "mean": 1.000000, "std": 0.000000 } , { "start_pos": 2960, "stop_pos": 3000,  "max": 2.000000, "min": 0.000000, "median": 1.000000, "avg": 0.650000, "mean": 0.650000, "std": 0.614410 } , { "start_pos": 3000, "stop_pos": 3040,  "max": 0.000000, "min": 0.000000, "median": 0.000000, "avg": 0.000000, "mean": 0.000000, "std": 0.000000 } , { "start_pos": 3040, "stop_pos": 3080,  "max": 1.000000, "min": 0.000000, "median": 0.000000, "avg": 0.325000, "mean": 0.325000, "std": 0.468375 } , { "start_pos": 3080, "stop_pos": 3120,  "max": 1.000000, "min": 0.000000, "median": 0.000000, "avg": 0.050000, "mean": 0.050000, "std": 0.217945 } , { "start_pos": 3120, "stop_pos": 3160,  "max": 0.000000, "min": 0.000000, "median": 0.000000, "avg": 0.000000, "mean": 0.000000, "std": 0.000000 } , { "start_pos": 3160, "stop_pos": 3200,  "max": 1.000000, "min": 0.000000, "median": 1.000000, "avg": 0.725000, "mean": 0.725000, "std": 0.446514 } , { "start_pos": 3200, "stop_pos": 3240,  "max": 2.000000, "min": 1.000000, "median": 1.000000, "avg": 1.125000, "mean": 1.125000, "std": 0.330719 } , { "start_pos": 3240, "stop_pos": 3280,  "max": 1.000000, "min": 0.000000, "median": 1.000000, "avg": 0.650000, "mean": 0.650000, "std": 0.476970 } , { "start_pos": 3280, "stop_pos": 3320,  "max": 3.000000, "min": 1.000000, "median": 1.000000, "avg": 1.625000, "mean": 1.625000, "std": 0.731010 } , { "start_pos": 3320, "stop_pos": 3360,  "max": 4.000000, "min": 1.000000, "median": 2.000000, "avg": 2.450000, "mean": 2.450000, "std": 0.973396 } , { "start_pos": 3360, "stop_pos": 3400,  "max": 2.000000, "min": 1.000000, "median": 1.000000, "avg": 1.250000, "mean": 1.250000, "std": 0.433013 } , { "start_pos": 3400, "stop_pos": 3440,  "max": 2.000000, "min": 2.000000, "median": 2.000000, "avg": 2.000000, "mean": 2.000000, "std": 0.000000 } , { "start_pos": 3440, "stop_pos": 3480,  "max": 3.000000, "min": 2.000000, "median": 2.000000, "avg": 2.475000, "mean": 2.475000, "std": 0.499375 } , { "start_pos": 3480, "stop_pos": 3520,  "max": 5.000000, "min": 3.000000, "median": 4.000000, "avg": 4.000000, "mean": 4.000000, "std": 0.741620 } , { "start_pos": 3520, "stop_pos": 3560,  "max": 4.000000, "min": 3.000000, "median": 3.000000, "avg": 3.450000, "mean": 3.450000, "std": 0.497494 } , { "start_pos": 3560, "stop_pos": 3600,  "max": 3.000000, "min": 2.000000, "median": 3.000000, "avg": 2.525000, "mean": 2.525000, "std": 0.499375 } , { "start_pos": 3600, "stop_pos": 3640,  "max": 4.000000, "min": 1.000000, "median": 2.000000, "avg": 2.525000, "mean": 2.525000, "std": 0.774193 } , { "start_pos": 3640, "stop_pos": 3680,  "max": 2.000000, "min": 0.000000, "median": 2.000000, "avg": 1.525000, "mean": 1.525000, "std": 0.591080 } , { "start_pos": 3680, "stop_pos": 3720,  "max": 3.000000, "min": 1.000000, "median": 2.000000, "avg": 2.275000, "mean": 2.275000, "std": 0.670354 } , { "start_pos": 3720, "stop_pos": 3760,  "max": 4.000000, "min": 1.000000, "median": 2.000000, "avg": 2.125000, "mean": 2.125000, "std": 1.208046 } , { "start_pos": 3760, "stop_pos": 3800,  "max": 4.000000, "min": 2.000000, "median": 3.000000, "avg": 2.950000, "mean": 2.950000, "std": 0.545436 } , { "start_pos": 3800, "stop_pos": 3840,  "max": 5.000000, "min": 1.000000, "median": 2.500000, "avg": 2.550000, "mean": 2.550000, "std": 1.532155 } , { "start_pos": 3840, "stop_pos": 3880,  "max": 1.000000, "min": 0.000000, "median": 1.000000, "avg": 0.775000, "mean": 0.775000, "std": 0.417582 } , { "start_pos": 3880, "stop_pos": 3920,  "max": 3.000000, "min": 1.000000, "median": 2.000000, "avg": 2.000000, "mean": 2.000000, "std": 0.447214 } , { "start_pos": 3920, "stop_pos": 3960,  "max": 2.000000, "min": 1.000000, "median": 1.000000, "avg": 1.050000, "mean": 1.050000, "std": 0.217945 } , { "start_pos": 3960, "stop_pos": 4000,  "max": 5.000000, "min": 1.000000, "median": 2.000000, "avg": 2.175000, "mean": 2.175000, "std": 1.115516 } ], "data_protein": [  { "start_pos": 0, "stop_pos": 40,  "max": 133.000000, "min": 60.000000, "median": 86.500000, "avg": 89.150000, "mean": 89.150000, "std": 20.493353 } , { "start_pos": 40, "stop_pos": 80,  "max": 252.000000, "min": 138.000000, "median": 218.000000, "avg": 206.650000, "mean": 206.650000, "std": 34.657286 } , { "start_pos": 80, "stop_pos": 120,  "max": 277.000000, "min": 254.000000, "median": 266.000000, "avg": 265.875000, "mean": 265.875000, "std": 6.403856 } , { "start_pos": 120, "stop_pos": 160,  "max": 267.000000, "min": 217.000000, "median": 250.500000, "avg": 246.725000, "mean": 246.725000, "std": 14.298579 } , { "start_pos": 160, "stop_pos": 200,  "max": 221.000000, "min": 134.000000, "median": 174.000000, "avg": 176.000000, "mean": 176.000000, "std": 28.853076 } , { "start_pos": 200, "stop_pos": 240,  "max": 132.000000, "min": 96.000000, "median": 111.000000, "avg": 112.425000, "mean": 112.425000, "std": 9.674419 } , { "start_pos": 240, "stop_pos": 280,  "max": 97.000000, "min": 65.000000, "median": 81.000000, "avg": 81.625000, "mean": 81.625000, "std": 11.116851 } , { "start_pos": 280, "stop_pos": 320,  "max": 65.000000, "min": 36.000000, "median": 51.500000, "avg": 51.525000, "mean": 51.525000, "std": 9.327346 } , { "start_pos": 320, "stop_pos": 360,  "max": 37.000000, "min": 25.000000, "median": 30.000000, "avg": 30.375000, "mean": 30.375000, "std": 4.258447 } , { "start_pos": 360, "stop_pos": 400,  "max": 27.000000, "min": 15.000000, "median": 18.000000, "avg": 18.575000, "mean": 18.575000, "std": 3.353263 } , { "start_pos": 400, "stop_pos": 440,  "max": 19.000000, "min": 15.000000, "median": 17.000000, "avg": 17.050000, "mean": 17.050000, "std": 0.893029 } , { "start_pos": 440, "stop_pos": 480,  "max": 23.000000, "min": 15.000000, "median": 20.000000, "avg": 19.525000, "mean": 19.525000, "std": 2.213453 } , { "start_pos": 480, "stop_pos": 520,  "max": 21.000000, "min": 8.000000, "median": 15.000000, "avg": 14.175000, "mean": 14.175000, "std": 4.036629 } , { "start_pos": 520, "stop_pos": 560,  "max": 8.000000, "min": 5.000000, "median": 5.000000, "avg": 6.175000, "mean": 6.175000, "std": 1.358078 } , { "start_pos": 560, "stop_pos": 600,  "max": 5.000000, "min": 2.000000, "median": 4.000000, "avg": 3.450000, "mean": 3.450000, "std": 0.835165 } , { "start_pos": 600, "stop_pos": 640,  "max": 14.000000, "min": 2.000000, "median": 9.000000, "avg": 8.350000, "mean": 8.350000, "std": 4.174626 } , { "start_pos": 640, "stop_pos": 680,  "max": 10.000000, "min": 5.000000, "median": 8.000000, "avg": 7.600000, "mean": 7.600000, "std": 1.854724 } , { "start_pos": 680, "stop_pos": 720,  "max": 25.000000, "min": 5.000000, "median": 14.000000, "avg": 12.975000, "mean": 12.975000, "std": 6.463310 } , { "start_pos": 720, "stop_pos": 760,  "max": 34.000000, "min": 25.000000, "median": 32.000000, "avg": 32.150000, "mean": 32.150000, "std": 2.043893 } , { "start_pos": 760, "stop_pos": 800,  "max": 30.000000, "min": 18.000000, "median": 24.000000, "avg": 24.025000, "mean": 24.025000, "std": 3.895430 } , { "start_pos": 800, "stop_pos": 840,  "max": 18.000000, "min": 9.000000, "median": 12.500000, "avg": 13.700000, "mean": 13.700000, "std": 2.925748 } , { "start_pos": 840, "stop_pos": 880,  "max": 9.000000, "min": 7.000000, "median": 8.000000, "avg": 7.900000, "mean": 7.900000, "std": 0.860233 } , { "start_pos": 880, "stop_pos": 920,  "max": 7.000000, "min": 3.000000, "median": 4.000000, "avg": 4.175000, "mean": 4.175000, "std": 0.971790 } , { "start_pos": 920, "stop_pos": 960,  "max": 4.000000, "min": 0.000000, "median": 3.000000, "avg": 2.325000, "mean": 2.325000, "std": 1.664144 } , { "start_pos": 960, "stop_pos": 1000,  "max": 6.000000, "min": 2.000000, "median": 5.000000, "avg": 4.375000, "mean": 4.375000, "std": 1.426315 } , { "start_pos": 1000, "stop_pos": 1040,  "max": 5.000000, "min": 2.000000, "median": 3.000000, "avg": 3.500000, "mean": 3.500000, "std": 1.322876 } , { "start_pos": 1040, "stop_pos": 1080,  "max": 10.000000, "min": 1.000000, "median": 4.000000, "avg": 5.000000, "mean": 5.000000, "std": 3.485685 } , { "start_pos": 1080, "stop_pos": 1120,  "max": 21.000000, "min": 8.000000, "median": 13.000000, "avg": 14.225000, "mean": 14.225000, "std": 3.560109 } , { "start_pos": 1120, "stop_pos": 1160,  "max": 33.000000, "min": 17.000000, "median": 28.000000, "avg": 26.500000, "mean": 26.500000, "std": 5.118594 } , { "start_pos": 1160, "stop_pos": 1200,  "max": 29.000000, "min": 24.000000, "median": 26.000000, "avg": 25.975000, "mean": 25.975000, "std": 1.540901 } , { "start_pos": 1200, "stop_pos": 1240,  "max": 32.000000, "min": 26.000000, "median": 29.000000, "avg": 28.700000, "mean": 28.700000, "std": 1.846619 } , { "start_pos": 1240, "stop_pos": 1280,  "max": 55.000000, "min": 34.000000, "median": 46.000000, "avg": 44.825000, "mean": 44.825000, "std": 6.541741 } , { "start_pos": 1280, "stop_pos": 1320,  "max": 61.000000, "min": 48.000000, "median": 55.000000, "avg": 54.925000, "mean": 54.925000, "std": 3.524113 } , { "start_pos": 1320, "stop_pos": 1360,  "max": 48.000000, "min": 32.000000, "median": 38.000000, "avg": 39.350000, "mean": 39.350000, "std": 5.165027 } , { "start_pos": 1360, "stop_pos": 1400,  "max": 32.000000, "min": 14.000000, "median": 21.500000, "avg": 21.825000, "mean": 21.825000, "std": 4.774346 } , { "start_pos": 1400, "stop_pos": 1440,  "max": 19.000000, "min": 12.000000, "median": 14.000000, "avg": 14.700000, "mean": 14.700000, "std": 2.088061 } , { "start_pos": 1440, "stop_pos": 1480,  "max": 22.000000, "min": 19.000000, "median": 21.000000, "avg": 20.925000, "mean": 20.925000, "std": 0.984568 } , { "start_pos": 1480, "stop_pos": 1520,  "max": 19.000000, "min": 8.000000, "median": 11.500000, "avg": 13.350000, "mean": 13.350000, "std": 3.275286 } , { "start_pos": 1520, "stop_pos": 1560,  "max": 18.000000, "min": 7.000000, "median": 13.000000, "avg": 12.225000, "mean": 12.225000, "std": 3.482007 } , { "start_pos": 1560, "stop_pos": 1600,  "max": 25.000000, "min": 19.000000, "median": 21.000000, "avg": 21.625000, "mean": 21.625000, "std": 1.698345 } , { "start_pos": 1600, "stop_pos": 1640,  "max": 29.000000, "min": 23.000000, "median": 26.000000, "avg": 26.175000, "mean": 26.175000, "std": 1.882651 } , { "start_pos": 1640, "stop_pos": 1680,  "max": 26.000000, "min": 21.000000, "median": 24.000000, "avg": 23.725000, "mean": 23.725000, "std": 1.532767 } , { "start_pos": 1680, "stop_pos": 1720,  "max": 24.000000, "min": 19.000000, "median": 21.000000, "avg": 21.100000, "mean": 21.100000, "std": 1.445683 } , { "start_pos": 1720, "stop_pos": 1760,  "max": 18.000000, "min": 10.000000, "median": 15.000000, "avg": 14.450000, "mean": 14.450000, "std": 2.519425 } , { "start_pos": 1760, "stop_pos": 1800,  "max": 11.000000, "min": 8.000000, "median": 9.000000, "avg": 9.225000, "mean": 9.225000, "std": 1.083686 } , { "start_pos": 1800, "stop_pos": 1840,  "max": 8.000000, "min": 3.000000, "median": 5.000000, "avg": 5.475000, "mean": 5.475000, "std": 1.322639 } , { "start_pos": 1840, "stop_pos": 1880,  "max": 3.000000, "min": 1.000000, "median": 3.000000, "avg": 2.250000, "mean": 2.250000, "std": 0.915150 } , { "start_pos": 1880, "stop_pos": 1920,  "max": 9.000000, "min": 1.000000, "median": 7.500000, "avg": 6.275000, "mean": 6.275000, "std": 2.269223 } , { "start_pos": 1920, "stop_pos": 1960,  "max": 20.000000, "min": 8.000000, "median": 16.000000, "avg": 15.150000, "mean": 15.150000, "std": 3.609363 } , { "start_pos": 1960, "stop_pos": 2000,  "max": 20.000000, "min": 14.000000, "median": 17.000000, "avg": 16.775000, "mean": 16.775000, "std": 1.981004 } , { "start_pos": 2000, "stop_pos": 2040,  "max": 16.000000, "min": 12.000000, "median": 15.000000, "avg": 14.300000, "mean": 14.300000, "std": 1.100000 } , { "start_pos": 2040, "stop_pos": 2080,  "max": 17.000000, "min": 13.000000, "median": 14.000000, "avg": 14.375000, "mean": 14.375000, "std": 1.218349 } , { "start_pos": 2080, "stop_pos": 2120,  "max": 16.000000, "min": 10.000000, "median": 13.000000, "avg": 12.625000, "mean": 12.625000, "std": 2.069873 } , { "start_pos": 2120, "stop_pos": 2160,  "max": 11.000000, "min": 7.000000, "median": 9.000000, "avg": 8.850000, "mean": 8.850000, "std": 1.351851 } , { "start_pos": 2160, "stop_pos": 2200,  "max": 27.000000, "min": 11.000000, "median": 16.000000, "avg": 17.675000, "mean": 17.675000, "std": 4.895853 } , { "start_pos": 2200, "stop_pos": 2240,  "max": 32.000000, "min": 23.000000, "median": 28.000000, "avg": 27.400000, "mean": 27.400000, "std": 2.507987 } , { "start_pos": 2240, "stop_pos": 2280,  "max": 23.000000, "min": 12.000000, "median": 19.000000, "avg": 18.400000, "mean": 18.400000, "std": 3.284814 } , { "start_pos": 2280, "stop_pos": 2320,  "max": 21.000000, "min": 11.000000, "median": 15.000000, "avg": 15.550000, "mean": 15.550000, "std": 2.635811 } , { "start_pos": 2320, "stop_pos": 2360,  "max": 26.000000, "min": 19.000000, "median": 22.000000, "avg": 22.200000, "mean": 22.200000, "std": 2.111871 } , { "start_pos": 2360, "stop_pos": 2400,  "max": 26.000000, "min": 15.000000, "median": 19.000000, "avg": 19.950000, "mean": 19.950000, "std": 2.397394 } , { "start_pos": 2400, "stop_pos": 2440,  "max": 15.000000, "min": 8.000000, "median": 11.000000, "avg": 10.825000, "mean": 10.825000, "std": 1.671638 } , { "start_pos": 2440, "stop_pos": 2480,  "max": 25.000000, "min": 9.000000, "median": 14.000000, "avg": 15.750000, "mean": 15.750000, "std": 5.342050 } , { "start_pos": 2480, "stop_pos": 2520,  "max": 26.000000, "min": 20.000000, "median": 23.000000, "avg": 22.725000, "mean": 22.725000, "std": 1.857249 } , { "start_pos": 2520, "stop_pos": 2560,  "max": 34.000000, "min": 20.000000, "median": 26.500000, "avg": 26.475000, "mean": 26.475000, "std": 4.658259 } , { "start_pos": 2560, "stop_pos": 2600,  "max": 43.000000, "min": 33.000000, "median": 37.000000, "avg": 37.575000, "mean": 37.575000, "std": 2.300951 } , { "start_pos": 2600, "stop_pos": 2640,  "max": 43.000000, "min": 33.000000, "median": 36.500000, "avg": 36.900000, "mean": 36.900000, "std": 2.947881 } , { "start_pos": 2640, "stop_pos": 2680,  "max": 35.000000, "min": 15.000000, "median": 22.500000, "avg": 22.675000, "mean": 22.675000, "std": 6.612063 } , { "start_pos": 2680, "stop_pos": 2720,  "max": 23.000000, "min": 15.000000, "median": 18.500000, "avg": 18.800000, "mean": 18.800000, "std": 3.210919 } , { "start_pos": 2720, "stop_pos": 2760,  "max": 24.000000, "min": 19.000000, "median": 21.000000, "avg": 20.625000, "mean": 20.625000, "std": 0.992157 } , { "start_pos": 2760, "stop_pos": 2800,  "max": 40.000000, "min": 24.000000, "median": 28.000000, "avg": 29.875000, "mean": 29.875000, "std": 4.202306 } , { "start_pos": 2800, "stop_pos": 2840,  "max": 55.000000, "min": 42.000000, "median": 51.000000, "avg": 50.250000, "mean": 50.250000, "std": 3.238441 } , { "start_pos": 2840, "stop_pos": 2880,  "max": 57.000000, "min": 43.000000, "median": 52.000000, "avg": 51.475000, "mean": 51.475000, "std": 3.905045 } , { "start_pos": 2880, "stop_pos": 2920,  "max": 47.000000, "min": 35.000000, "median": 43.000000, "avg": 41.750000, "mean": 41.750000, "std": 3.603817 } , { "start_pos": 2920, "stop_pos": 2960,  "max": 39.000000, "min": 28.000000, "median": 35.000000, "avg": 33.675000, "mean": 33.675000, "std": 3.085348 } , { "start_pos": 2960, "stop_pos": 3000,  "max": 31.000000, "min": 17.000000, "median": 26.000000, "avg": 24.900000, "mean": 24.900000, "std": 4.259108 } , { "start_pos": 3000, "stop_pos": 3040,  "max": 17.000000, "min": 13.000000, "median": 14.000000, "avg": 14.175000, "mean": 14.175000, "std": 1.320748 } , { "start_pos": 3040, "stop_pos": 3080,  "max": 13.000000, "min": 11.000000, "median": 12.000000, "avg": 12.150000, "mean": 12.150000, "std": 0.653835 } , { "start_pos": 3080, "stop_pos": 3120,  "max": 11.000000, "min": 7.000000, "median": 8.000000, "avg": 7.850000, "mean": 7.850000, "std": 0.988686 } , { "start_pos": 3120, "stop_pos": 3160,  "max": 7.000000, "min": 3.000000, "median": 6.500000, "avg": 5.800000, "mean": 5.800000, "std": 1.519868 } , { "start_pos": 3160, "stop_pos": 3200,  "max": 3.000000, "min": 3.000000, "median": 3.000000, "avg": 3.000000, "mean": 3.000000, "std": 0.000000 } , { "start_pos": 3200, "stop_pos": 3240,  "max": 11.000000, "min": 3.000000, "median": 9.000000, "avg": 8.325000, "mean": 8.325000, "std": 2.004838 } , { "start_pos": 3240, "stop_pos": 3280,  "max": 14.000000, "min": 9.000000, "median": 11.000000, "avg": 11.525000, "mean": 11.525000, "std": 1.532767 } , { "start_pos": 3280, "stop_pos": 3320,  "max": 18.000000, "min": 11.000000, "median": 13.000000, "avg": 13.400000, "mean": 13.400000, "std": 1.813836 } , { "start_pos": 3320, "stop_pos": 3360,  "max": 28.000000, "min": 16.000000, "median": 23.000000, "avg": 22.375000, "mean": 22.375000, "std": 3.344305 } , { "start_pos": 3360, "stop_pos": 3400,  "max": 29.000000, "min": 18.000000, "median": 25.000000, "avg": 24.025000, "mean": 24.025000, "std": 3.843745 } , { "start_pos": 3400, "stop_pos": 3440,  "max": 27.000000, "min": 18.000000, "median": 22.000000, "avg": 22.925000, "mean": 22.925000, "std": 2.705434 } , { "start_pos": 3440, "stop_pos": 3480,  "max": 25.000000, "min": 21.000000, "median": 23.000000, "avg": 23.125000, "mean": 23.125000, "std": 1.053269 } , { "start_pos": 3480, "stop_pos": 3520,  "max": 41.000000, "min": 24.000000, "median": 36.000000, "avg": 33.350000, "mean": 33.350000, "std": 5.628277 } , { "start_pos": 3520, "stop_pos": 3560,  "max": 49.000000, "min": 39.000000, "median": 44.000000, "avg": 44.025000, "mean": 44.025000, "std": 2.724771 } , { "start_pos": 3560, "stop_pos": 3600,  "max": 44.000000, "min": 36.000000, "median": 39.000000, "avg": 39.275000, "mean": 39.275000, "std": 1.870662 } , { "start_pos": 3600, "stop_pos": 3640,  "max": 41.000000, "min": 26.000000, "median": 31.000000, "avg": 32.875000, "mean": 32.875000, "std": 4.567206 } , { "start_pos": 3640, "stop_pos": 3680,  "max": 35.000000, "min": 29.000000, "median": 33.000000, "avg": 32.325000, "mean": 32.325000, "std": 1.967073 } , { "start_pos": 3680, "stop_pos": 3720,  "max": 37.000000, "min": 28.000000, "median": 32.000000, "avg": 32.075000, "mean": 32.075000, "std": 2.866945 } , { "start_pos": 3720, "stop_pos": 3760,  "max": 37.000000, "min": 24.000000, "median": 30.000000, "avg": 30.150000, "mean": 30.150000, "std": 3.837643 } , { "start_pos": 3760, "stop_pos": 3800,  "max": 43.000000, "min": 30.000000, "median": 38.000000, "avg": 36.975000, "mean": 36.975000, "std": 3.629652 } , { "start_pos": 3800, "stop_pos": 3840,  "max": 46.000000, "min": 32.000000, "median": 37.000000, "avg": 38.500000, "mean": 38.500000, "std": 4.043513 } , { "start_pos": 3840, "stop_pos": 3880,  "max": 34.000000, "min": 20.000000, "median": 26.500000, "avg": 26.675000, "mean": 26.675000, "std": 4.823834 } , { "start_pos": 3880, "stop_pos": 3920,  "max": 26.000000, "min": 16.000000, "median": 19.500000, "avg": 20.075000, "mean": 20.075000, "std": 3.635846 } , { "start_pos": 3920, "stop_pos": 3960,  "max": 26.000000, "min": 20.000000, "median": 24.000000, "avg": 23.475000, "mean": 23.475000, "std": 1.788680 } , { "start_pos": 3960, "stop_pos": 4000,  "max": 27.000000, "min": 16.000000, "median": 20.000000, "avg": 20.325000, "mean": 20.325000, "std": 2.601802 } ] }
