{ "URDMEModel" : "1f104fde-eebe-11e4-ad13-fa163e25d342", "windows_size": 40, "data_Pf": [  { "start_pos": 0, "stop_pos": 40,  "max": 1.000000, "min": 0.000000, "median": 1.000000, "avg": 0.650000, "mean": 0.650000, "std": 0.476970 } , { "start_pos": 40, "stop_pos": 80,  "max": 0.000000, "min": 0.000000, "median": 0.000000, "avg": 0.000000, "mean": 0.000000, "std": 0.000000 } , { "start_pos": 80, "stop_pos": 120,  "max": 0.000000, "min": 0.000000, "median": 0.000000, "avg": 0.000000, "mean": 0.000000, "std": 0.000000 } , { "start_pos": 120, "stop_pos": 160,  "max": 0.000000, "min": 0.000000, "median": 0.000000, "avg": 0.000000, "mean": 0.000000, "std": 0.000000 } , { "start_pos": 160, "stop_pos": 200,  "max": 0.000000, "min": 0.000000, "median": 0.000000, "avg": 0.000000, "mean": 0.000000, "std": 0.000000 } , { "start_pos": 200, "stop_pos": 240,  "max": 0.000000, "min": 0.000000, "median": 0.000000, "avg": 0.000000, "mean": 0.000000, "std": 0.000000 } , { "start_pos": 240, "stop_pos": 280,  "max": 0.000000, "min": 0.000000, "median": 0.000000, "avg": 0.000000, "mean": 0.000000, "std": 0.000000 } , { "start_pos": 280, "stop_pos": 320,  "max": 0.000000, "min": 0.000000, "median": 0.000000, "avg": 0.000000, "mean": 0.000000, "std": 0.000000 } , { "start_pos": 320, "stop_pos": 360,  "max": 0.000000, "min": 0.000000, "median": 0.000000, "avg": 0.000000, "mean": 0.000000, "std": 0.000000 } , { "start_pos": 360, "stop_pos": 400,  "max": 0.000000, "min": 0.000000, "median": 0.000000, "avg": 0.000000, "mean": 0.000000, "std": 0.000000 } , { "start_pos": 400, "stop_pos": 440,  "max": 0.000000, "min": 0.000000, "median": 0.000000, "avg": 0.000000, "mean": 0.000000, "std": 0.000000 } , { "start_pos": 440, "stop_pos": 480,  "max": 0.000000, "min": 0.000000, "median": 0.000000, "avg": 0.000000, "mean": 0.000000, "std": 0.000000 } , { "start_pos": 480, "stop_pos": 520,  "max": 0.000000, "min": 0.000000, "median": 0.000000, "avg": 0.000000, "mean": 0.000000, "std": 0.000000 } , { "start_pos": 520, "stop_pos": 560,  "max": 0.000000, "min": 0.000000, "median": 0.000000, "avg": 0.000000, "mean": 0.000000, "std": 0.000000 } , { "start_pos": 560, "stop_pos": 600,  "max": 0.000000, "min": 0.000000, "median": 0.000000, "avg": 0.000000, "mean": 0.000000, "std": 0.000000 } , { "start_pos": 600, "stop_pos": 640,  "max": 0.000000, "min": 0.000000, "median": 0.000000, "avg": 0.000000, "mean": 0.000000, "std": 0.000000 } , { "start_pos": 640, "stop_pos": 680,  "max": 0.000000, "min": 0.000000, "median": 0.000000, "avg": 0.000000, "mean": 0.000000, "std": 0.000000 } , { "start_pos": 680, "stop_pos": 720,  "max": 0.000000, "min": 0.000000, "median": 0.000000, "avg": 0.000000, "mean": 0.000000, "std": 0.000000 } , { "start_pos": 720, "stop_pos": 760,  "max": 0.000000, "min": 0.000000, "median": 0.000000, "avg": 0.000000, "mean": 0.000000, "std": 0.000000 } , { "start_pos": 760, "stop_pos": 800,  "max": 0.000000, "min": 0.000000, "median": 0.000000, "avg": 0.000000, "mean": 0.000000, "std": 0.000000 } , { "start_pos": 800, "stop_pos": 840,  "max": 0.000000, "min": 0.000000, "median": 0.000000, "avg": 0.000000, "mean": 0.000000, "std": 0.000000 } , { "start_pos": 840, "stop_pos": 880,  "max": 0.000000, "min": 0.000000, "median": 0.000000, "avg": 0.000000, "mean": 0.000000, "std": 0.000000 } , { "start_pos": 880, "stop_pos": 920,  "max": 0.000000, "min": 0.000000, "median": 0.000000, "avg": 0.000000, "mean": 0.000000, "std": 0.000000 } , { "start_pos": 920, "stop_pos": 960,  "max": 0.000000, "min": 0.000000, "median": 0.000000, "avg": 0.000000, "mean": 0.000000, "std": 0.000000 } , { "start_pos": 960, "stop_pos": 1000,  "max": 0.000000, "min": 0.000000, "median": 0.000000, "avg": 0.000000, "mean": 0.000000, "std": 0.000000 } , { "start_pos": 1000, "stop_pos": 1040,  "max": 0.000000, "min": 0.000000, "median": 0.000000, "avg": 0.000000, "mean": 0.000000, "std": 0.000000 } , { "start_pos": 1040, "stop_pos": 1080,  "max": 0.000000, "min": 0.000000, "median": 0.000000, "avg": 0.000000, "mean": 0.000000, "std": 0.000000 } , { "start_pos": 1080, "stop_pos": 1120,  "max": 0.000000, "min": 0.000000, "median": 0.000000, "avg": 0.000000, "mean": 0.000000, "std": 0.000000 } , { "start_pos": 1120, "stop_pos": 1160,  "max": 0.000000, "min": 0.000000, "median": 0.000000, "avg": 0.000000, "mean": 0.000000, "std": 0.000000 } , { "start_pos": 1160, "stop_pos": 1200,  "max": 0.000000, "min": 0.000000, "median": 0.000000, "avg": 0.000000, "mean": 0.000000, "std": 0.000000 } , { "start_pos": 1200, "stop_pos": 1240,  "max": 0.000000, "min": 0.000000, "median": 0.000000, "avg": 0.000000, "mean": 0.000000, "std": 0.000000 } , { "start_pos": 1240, "stop_pos": 1280,  "max": 0.000000, "min": 0.000000, "median": 0.000000, "avg": 0.000000, "mean": 0.000000, "std": 0.000000 } , { "start_pos": 1280, "stop_pos": 1320,  "max": 0.000000, "min": 0.000000, "median": 0.000000, "avg": 0.000000, "mean": 0.000000, "std": 0.000000 } , { "start_pos": 1320, "stop_pos": 1360,  "max": 0.000000, "min": 0.000000, "median": 0.000000, "avg": 0.000000, "mean": 0.000000, "std": 0.000000 } , { "start_pos": 1360, "stop_pos": 1400,  "max": 0.000000, "min": 0.000000, "median": 0.000000, "avg": 0.000000, "mean": 0.000000, "std": 0.000000 } , { "start_pos": 1400, "stop_pos": 1440,  "max": 0.000000, "min": 0.000000, "median": 0.000000, "avg": 0.000000, "mean": 0.000000, "std": 0.000000 } , { "start_pos": 1440, "stop_pos": 1480,  "max": 0.000000, "min": 0.000000, "median": 0.000000, "avg": 0.000000, "mean": 0.000000, "std": 0.000000 } , { "start_pos": 1480, "stop_pos": 1520,  "max": 0.000000, "min": 0.000000, "median": 0.000000, "avg": 0.000000, "mean": 0.000000, "std": 0.000000 } , { "start_pos": 1520, "stop_pos": 1560,  "max": 0.000000, "min": 0.000000, "median": 0.000000, "avg": 0.000000, "mean": 0.000000, "std": 0.000000 } , { "start_pos": 1560, "stop_pos": 1600,  "max": 0.000000, "min": 0.000000, "median": 0.000000, "avg": 0.000000, "mean": 0.000000, "std": 0.000000 } , { "start_pos": 1600, "stop_pos": 1640,  "max": 0.000000, "min": 0.000000, "median": 0.000000, "avg": 0.000000, "mean": 0.000000, "std": 0.000000 } , { "start_pos": 1640, "stop_pos": 1680,  "max": 0.000000, "min": 0.000000, "median": 0.000000, "avg": 0.000000, "mean": 0.000000, "std": 0.000000 } , { "start_pos": 1680, "stop_pos": 1720,  "max": 0.000000, "min": 0.000000, "median": 0.000000, "avg": 0.000000, "mean": 0.000000, "std": 0.000000 } , { "start_pos": 1720, "stop_pos": 1760,  "max": 0.000000, "min": 0.000000, "median": 0.000000, "avg": 0.000000, "mean": 0.000000, "std": 0.000000 } , { "start_pos": 1760, "stop_pos": 1800,  "max": 0.000000, "min": 0.000000, "median": 0.000000, "avg": 0.000000, "mean": 0.000000, "std": 0.000000 } , { "start_pos": 1800, "stop_pos": 1840,  "max": 0.000000, "min": 0.000000, "median": 0.000000, "avg": 0.000000, "mean": 0.000000, "std": 0.000000 } , { "start_pos": 1840, "stop_pos": 1880,  "max": 0.000000, "min": 0.000000, "median": 0.000000, "avg": 0.000000, "mean": 0.000000, "std": 0.000000 } , { "start_pos": 1880, "stop_pos": 1920,  "max": 0.000000, "min": 0.000000, "median": 0.000000, "avg": 0.000000, "mean": 0.000000, "std": 0.000000 } , { "start_pos": 1920, "stop_pos": 1960,  "max": 0.000000, "min": 0.000000, "median": 0.000000, "avg": 0.000000, "mean": 0.000000, "std": 0.000000 } , { "start_pos": 1960, "stop_pos": 2000,  "max": 0.000000, "min": 0.000000, "median": 0.000000, "avg": 0.000000, "mean": 0.000000, "std": 0.000000 } , { "start_pos": 2000, "stop_pos": 2040,  "max": 0.000000, "min": 0.000000, "median": 0.000000, "avg": 0.000000, "mean": 0.000000, "std": 0.000000 } , { "start_pos": 2040, "stop_pos": 2080,  "max": 0.000000, "min": 0.000000, "median": 0.000000, "avg": 0.000000, "mean": 0.000000, "std": 0.000000 } , { "start_pos": 2080, "stop_pos": 2120,  "max": 0.000000, "min": 0.000000, "median": 0.000000, "avg": 0.000000, "mean": 0.000000, "std": 0.000000 } , { "start_pos": 2120, "stop_pos": 2160,  "max": 0.000000, "min": 0.000000, "median": 0.000000, "avg": 0.000000, "mean": 0.000000, "std": 0.000000 } , { "start_pos": 2160, "stop_pos": 2200,  "max": 0.000000, "min": 0.000000, "median": 0.000000, "avg": 0.000000, "mean": 0.000000, "std": 0.000000 } , { "start_pos": 2200, "stop_pos": 2240,  "max": 0.000000, "min": 0.000000, "median": 0.000000, "avg": 0.000000, "mean": 0.000000, "std": 0.000000 } , { "start_pos": 2240, "stop_pos": 2280,  "max": 0.000000, "min": 0.000000, "median": 0.000000, "avg": 0.000000, "mean": 0.000000, "std": 0.000000 } , { "start_pos": 2280, "stop_pos": 2320,  "max": 0.000000, "min": 0.000000, "median": 0.000000, "avg": 0.000000, "mean": 0.000000, "std": 0.000000 } , { "start_pos": 2320, "stop_pos": 2360,  "max": 0.000000, "min": 0.000000, "median": 0.000000, "avg": 0.000000, "mean": 0.000000, "std": 0.000000 } , { "start_pos": 2360, "stop_pos": 2400,  "max": 0.000000, "min": 0.000000, "median": 0.000000, "avg": 0.000000, "mean": 0.000000, "std": 0.000000 } , { "start_pos": 2400, "stop_pos": 2440,  "max": 0.000000, "min": 0.000000, "median": 0.000000, "avg": 0.000000, "mean": 0.000000, "std": 0.000000 } , { "start_pos": 2440, "stop_pos": 2480,  "max": 0.000000, "min": 0.000000, "median": 0.000000, "avg": 0.000000, "mean": 0.000000, "std": 0.000000 } , { "start_pos": 2480, "stop_pos": 2520,  "max": 0.000000, "min": 0.000000, "median": 0.000000, "avg": 0.000000, "mean": 0.000000, "std": 0.000000 } , { "start_pos": 2520, "stop_pos": 2560,  "max": 0.000000, "min": 0.000000, "median": 0.000000, "avg": 0.000000, "mean": 0.000000, "std": 0.000000 } , { "start_pos": 2560, "stop_pos": 2600,  "max": 0.000000, "min": 0.000000, "median": 0.000000, "avg": 0.000000, "mean": 0.000000, "std": 0.000000 } , { "start_pos": 2600, "stop_pos": 2640,  "max": 0.000000, "min": 0.000000, "median": 0.000000, "avg": 0.000000, "mean": 0.000000, "std": 0.000000 } , { "start_pos": 2640, "stop_pos": 2680,  "max": 0.000000, "min": 0.000000, "median": 0.000000, "avg": 0.000000, "mean": 0.000000, "std": 0.000000 } , { "start_pos": 2680, "stop_pos": 2720,  "max": 0.000000, "min": 0.000000, "median": 0.000000, "avg": 0.000000, "mean": 0.000000, "std": 0.000000 } , { "start_pos": 2720, "stop_pos": 2760,  "max": 0.000000, "min": 0.000000, "median": 0.000000, "avg": 0.000000, "mean": 0.000000, "std": 0.000000 } , { "start_pos": 2760, "stop_pos": 2800,  "max": 0.000000, "min": 0.000000, "median": 0.000000, "avg": 0.000000, "mean": 0.000000, "std": 0.000000 } , { "start_pos": 2800, "stop_pos": 2840,  "max": 0.000000, "min": 0.000000, "median": 0.000000, "avg": 0.000000, "mean": 0.000000, "std": 0.000000 } , { "start_pos": 2840, "stop_pos": 2880,  "max": 0.000000, "min": 0.000000, "median": 0.000000, "avg": 0.000000, "mean": 0.000000, "std": 0.000000 } , { "start_pos": 2880, "stop_pos": 2920,  "max": 0.000000, "min": 0.000000, "median": 0.000000, "avg": 0.000000, "mean": 0.000000, "std": 0.000000 } , { "start_pos": 2920, "stop_pos": 2960,  "max": 0.000000, "min": 0.000000, "median": 0.000000, "avg": 0.000000, "mean": 0.000000, "std": 0.000000 } , { "start_pos": 2960, "stop_pos": 3000,  "max": 0.000000, "min": 0.000000, "median": 0.000000, "avg": 0.000000, "mean": 0.000000, "std": 0.000000 } , { "start_pos": 3000, "stop_pos": 3040,  "max": 0.000000, "min": 0.000000, "median": 0.000000, "avg": 0.000000, "mean": 0.000000, "std": 0.000000 } , { "start_pos": 3040, "stop_pos": 3080,  "max": 0.000000, "min": 0.000000, "median": 0.000000, "avg": 0.000000, "mean": 0.000000, "std": 0.000000 } , { "start_pos": 3080, "stop_pos": 3120,  "max": 0.000000, "min": 0.000000, "median": 0.000000, "avg": 0.000000, "mean": 0.000000, "std": 0.000000 } , { "start_pos": 3120, "stop_pos": 3160,  "max": 0.000000, "min": 0.000000, "median": 0.000000, "avg": 0.000000, "mean": 0.000000, "std": 0.000000 } , { "start_pos": 3160, "stop_pos": 3200,  "max": 0.000000, "min": 0.000000, "median": 0.000000, "avg": 0.000000, "mean": 0.000000, "std": 0.000000 } , { "start_pos": 3200, "stop_pos": 3240,  "max": 0.000000, "min": 0.000000, "median": 0.000000, "avg": 0.000000, "mean": 0.000000, "std": 0.000000 } , { "start_pos": 3240, "stop_pos": 3280,  "max": 0.000000, "min": 0.000000, "median": 0.000000, "avg": 0.000000, "mean": 0.000000, "std": 0.000000 } , { "start_pos": 3280, "stop_pos": 3320,  "max": 0.000000, "min": 0.000000, "median": 0.000000, "avg": 0.000000, "mean": 0.000000, "std": 0.000000 } , { "start_pos": 3320, "stop_pos": 3360,  "max": 0.000000, "min": 0.000000, "median": 0.000000, "avg": 0.000000, "mean": 0.000000, "std": 0.000000 } , { "start_pos": 3360, "stop_pos": 3400,  "max": 0.000000, "min": 0.000000, "median": 0.000000, "avg": 0.000000, "mean": 0.000000, "std": 0.000000 } , { "start_pos": 3400, "stop_pos": 3440,  "max": 0.000000, "min": 0.000000, "median": 0.000000, "avg": 0.000000, "mean": 0.000000, "std": 0.000000 } , { "start_pos": 3440, "stop_pos": 3480,  "max": 0.000000, "min": 0.000000, "median": 0.000000, "avg": 0.000000, "mean": 0.000000, "std": 0.000000 } , { "start_pos": 3480, "stop_pos": 3520,  "max": 0.000000, "min": 0.000000, "median": 0.000000, "avg": 0.000000, "mean": 0.000000, "std": 0.000000 } , { "start_pos": 3520, "stop_pos": 3560,  "max": 0.000000, "min": 0.000000, "median": 0.000000, "avg": 0.000000, "mean": 0.000000, "std": 0.000000 } , { "start_pos": 3560, "stop_pos": 3600,  "max": 0.000000, "min": 0.000000, "median": 0.000000, "avg": 0.000000, "mean": 0.000000, "std": 0.000000 } , { "start_pos": 3600, "stop_pos": 3640,  "max": 0.000000, "min": 0.000000, "median": 0.000000, "avg": 0.000000, "mean": 0.000000, "std": 0.000000 } , { "start_pos": 3640, "stop_pos": 3680,  "max": 0.000000, "min": 0.000000, "median": 0.000000, "avg": 0.000000, "mean": 0.000000, "std": 0.000000 } , { "start_pos": 3680, "stop_pos": 3720,  "max": 0.000000, "min": 0.000000, "median": 0.000000, "avg": 0.000000, "mean": 0.000000, "std": 0.000000 } , { "start_pos": 3720, "stop_pos": 3760,  "max": 0.000000, "min": 0.000000, "median": 0.000000, "avg": 0.000000, "mean": 0.000000, "std": 0.000000 } , { "start_pos": 3760, "stop_pos": 3800,  "max": 0.000000, "min": 0.000000, "median": 0.000000, "avg": 0.000000, "mean": 0.000000, "std": 0.000000 } , { "start_pos": 3800, "stop_pos": 3840,  "max": 0.000000, "min": 0.000000, "median": 0.000000, "avg": 0.000000, "mean": 0.000000, "std": 0.000000 } , { "start_pos": 3840, "stop_pos": 3880,  "max": 0.000000, "min": 0.000000, "median": 0.000000, "avg": 0.000000, "mean": 0.000000, "std": 0.000000 } , { "start_pos": 3880, "stop_pos": 3920,  "max": 0.000000, "min": 0.000000, "median": 0.000000, "avg": 0.000000, "mean": 0.000000, "std": 0.000000 } , { "start_pos": 3920, "stop_pos": 3960,  "max": 0.000000, "min": 0.000000, "median": 0.000000, "avg": 0.000000, "mean": 0.000000, "std": 0.000000 } , { "start_pos": 3960, "stop_pos": 4000,  "max": 0.000000, "min": 0.000000, "median": 0.000000, "avg": 0.000000, "mean": 0.000000, "std": 0.000000 } ], "data_Po": [  { "start_pos": 0, "stop_pos": 40,  "max": 1.000000, "min": 0.000000, "median": 0.000000, "avg": 0.350000, "mean": 0.350000, "std": 0.476970 } , { "start_pos": 40, "stop_pos": 80,  "max": 1.000000, "min": 1.000000, "median": 1.000000, "avg": 1.000000, "mean": 1.000000, "std": 0.000000 } , { "start_pos": 80, "stop_pos": 120,  "max": 1.000000, "min": 1.000000, "median": 1.000000, "avg": 1.000000, "mean": 1.000000, "std": 0.000000 } , { "start_pos": 120, "stop_pos": 160,  "max": 1.000000, "min": 1.000000, "median": 1.000000, "avg": 1.000000, "mean": 1.000000, "std": 0.000000 } , { "start_pos": 160, "stop_pos": 200,  "max": 1.000000, "min": 1.000000, "median": 1.000000, "avg": 1.000000, "mean": 1.000000, "std": 0.000000 } , { "start_pos": 200, "stop_pos": 240,  "max": 1.000000, "min": 1.000000, "median": 1.000000, "avg": 1.000000, "mean": 1.000000, "std": 0.000000 } , { "start_pos": 240, "stop_pos": 280,  "max": 1.000000, "min": 1.000000, "median": 1.000000, "avg": 1.000000, "mean": 1.000000, "std": 0.000000 } , { "start_pos": 280, "stop_pos": 320,  "max": 1.000000, "min": 1.000000, "median": 1.000000, "avg": 1.000000, "mean": 1.000000, "std": 0.000000 } , { "start_pos": 320, "stop_pos": 360,  "max": 1.000000, "min": 1.000000, "median": 1.000000, "avg": 1.000000, "mean": 1.000000, "std": 0.000000 } , { "start_pos": 360, "stop_pos": 400,  "max": 1.000000, "min": 1.000000, "median": 1.000000, "avg": 1.000000, "mean": 1.000000, "std": 0.000000 } , { "start_pos": 400, "stop_pos": 440,  "max": 1.000000, "min": 1.000000, "median": 1.000000, "avg": 1.000000, "mean": 1.000000, "std": 0.000000 } , { "start_pos": 440, "stop_pos": 480,  "max": 1.000000, "min": 1.000000, "median": 1.000000, "avg": 1.000000, "mean": 1.000000, "std": 0.000000 } , { "start_pos": 480, "stop_pos": 520,  "max": 1.000000, "min": 1.000000, "median": 1.000000, "avg": 1.000000, "mean": 1.000000, "std": 0.000000 } , { "start_pos": 520, "stop_pos": 560,  "max": 1.000000, "min": 1.000000, "median": 1.000000, "avg": 1.000000, "mean": 1.000000, "std": 0.000000 } , { "start_pos": 560, "stop_pos": 600,  "max": 1.000000, "min": 1.000000, "median": 1.000000, "avg": 1.000000, "mean": 1.000000, "std": 0.000000 } , { "start_pos": 600, "stop_pos": 640,  "max": 1.000000, "min": 1.000000, "median": 1.000000, "avg": 1.000000, "mean": 1.000000, "std": 0.000000 } , { "start_pos": 640, "stop_pos": 680,  "max": 1.000000, "min": 1.000000, "median": 1.000000, "avg": 1.000000, "mean": 1.000000, "std": 0.000000 } , { "start_pos": 680, "stop_pos": 720,  "max": 1.000000, "min": 1.000000, "median": 1.000000, "avg": 1.000000, "mean": 1.000000, "std": 0.000000 } , { "start_pos": 720, "stop_pos": 760,  "max": 1.000000, "min": 1.000000, "median": 1.000000, "avg": 1.000000, "mean": 1.000000, "std": 0.000000 } , { "start_pos": 760, "stop_pos": 800,  "max": 1.000000, "min": 1.000000, "median": 1.000000, "avg": 1.000000, "mean": 1.000000, "std": 0.000000 } , { "start_pos": 800, "stop_pos": 840,  "max": 1.000000, "min": 1.000000, "median": 1.000000, "avg": 1.000000, "mean": 1.000000, "std": 0.000000 } , { "start_pos": 840, "stop_pos": 880,  "max": 1.000000, "min": 1.000000, "median": 1.000000, "avg": 1.000000, "mean": 1.000000, "std": 0.000000 } , { "start_pos": 880, "stop_pos": 920,  "max": 1.000000, "min": 1.000000, "median": 1.000000, "avg": 1.000000, "mean": 1.000000, "std": 0.000000 } , { "start_pos": 920, "stop_pos": 960,  "max": 1.000000, "min": 1.000000, "median": 1.000000, "avg": 1.000000, "mean": 1.000000, "std": 0.000000 } , { "start_pos": 960, "stop_pos": 1000,  "max": 1.000000, "min": 1.000000, "median": 1.000000, "avg": 1.000000, "mean": 1.000000, "std": 0.000000 } , { "start_pos": 1000, "stop_pos": 1040,  "max": 1.000000, "min": 1.000000, "median": 1.000000, "avg": 1.000000, "mean": 1.000000, "std": 0.000000 } , { "start_pos": 1040, "stop_pos": 1080,  "max": 1.000000, "min": 1.000000, "median": 1.000000, "avg": 1.000000, "mean": 1.000000, "std": 0.000000 } , { "start_pos": 1080, "stop_pos": 1120,  "max": 1.000000, "min": 1.000000, "median": 1.000000, "avg": 1.000000, "mean": 1.000000, "std": 0.000000 } , { "start_pos": 1120, "stop_pos": 1160,  "max": 1.000000, "min": 1.000000, "median": 1.000000, "avg": 1.000000, "mean": 1.000000, "std": 0.000000 } , { "start_pos": 1160, "stop_pos": 1200,  "max": 1.000000, "min": 1.000000, "median": 1.000000, "avg": 1.000000, "mean": 1.000000, "std": 0.000000 } , { "start_pos": 1200, "stop_pos": 1240,  "max": 1.000000, "min": 1.000000, "median": 1.000000, "avg": 1.000000, "mean": 1.000000, "std": 0.000000 } , { "start_pos": 1240, "stop_pos": 1280,  "max": 1.000000, "min": 1.000000, "median": 1.000000, "avg": 1.000000, "mean": 1.000000, "std": 0.000000 } , { "start_pos": 1280, "stop_pos": 1320,  "max": 1.000000, "min": 1.000000, "median": 1.000000, "avg": 1.000000, "mean": 1.000000, "std": 0.000000 } , { "start_pos": 1320, "stop_pos": 1360,  "max": 1.000000, "min": 1.000000, "median": 1.000000, "avg": 1.000000, "mean": 1.000000, "std": 0.000000 } , { "start_pos": 1360, "stop_pos": 1400,  "max": 1.000000, "min": 1.000000, "median": 1.000000, "avg": 1.000000, "mean": 1.000000, "std": 0.000000 } , { "start_pos": 1400, "stop_pos": 1440,  "max": 1.000000, "min": 1.000000, "median": 1.000000, "avg": 1.000000, "mean": 1.000000, "std": 0.000000 } , { "start_pos": 1440, "stop_pos": 1480,  "max": 1.000000, "min": 1.000000, "median": 1.000000, "avg": 1.000000, "mean": 1.000000, "std": 0.000000 } , { "start_pos": 1480, "stop_pos": 1520,  "max": 1.000000, "min": 1.000000, "median": 1.000000, "avg": 1.000000, "mean": 1.000000, "std": 0.000000 } , { "start_pos": 1520, "stop_pos": 1560,  "max": 1.000000, "min": 1.000000, "median": 1.000000, "avg": 1.000000, "mean": 1.000000, "std": 0.000000 } , { "start_pos": 1560, "stop_pos": 1600,  "max": 1.000000, "min": 1.000000, "median": 1.000000, "avg": 1.000000, "mean": 1.000000, "std": 0.000000 } , { "start_pos": 1600, "stop_pos": 1640,  "max": 1.000000, "min": 1.000000, "median": 1.000000, "avg": 1.000000, "mean": 1.000000, "std": 0.000000 } , { "start_pos": 1640, "stop_pos": 1680,  "max": 1.000000, "min": 1.000000, "median": 1.000000, "avg": 1.000000, "mean": 1.000000, "std": 0.000000 } , { "start_pos": 1680, "stop_pos": 1720,  "max": 1.000000, "min": 1.000000, "median": 1.000000, "avg": 1.000000, "mean": 1.000000, "std": 0.000000 } , { "start_pos": 1720, "stop_pos": 1760,  "max": 1.000000, "min": 1.000000, "median": 1.000000, "avg": 1.000000, "mean": 1.000000, "std": 0.000000 } , { "start_pos": 1760, "stop_pos": 1800,  "max": 1.000000, "min": 1.000000, "median": 1.000000, "avg": 1.000000, "mean": 1.000000, "std": 0.000000 } , { "start_pos": 1800, "stop_pos": 1840,  "max": 1.000000, "min": 1.000000, "median": 1.000000, "avg": 1.000000, "mean": 1.000000, "std": 0.000000 } , { "start_pos": 1840, "stop_pos": 1880,  "max": 1.000000, "min": 1.000000, "median": 1.000000, "avg": 1.000000, "mean": 1.000000, "std": 0.000000 } , { "start_pos": 1880, "stop_pos": 1920,  "max": 1.000000, "min": 1.000000, "median": 1.000000, "avg": 1.000000, "mean": 1.000000, "std": 0.000000 } , { "start_pos": 1920, "stop_pos": 1960,  "max": 1.000000, "min": 1.000000, "median": 1.000000, "avg": 1.000000, "mean": 1.000000, "std": 0.000000 } , { "start_pos": 1960, "stop_pos": 2000,  "max": 1.000000, "min": 1.000000, "median": 1.000000, "avg": 1.000000, "mean": 1.000000, "std": 0.000000 } , { "start_pos": 2000, "stop_pos": 2040,  "max": 1.000000, "min": 1.000000, "median": 1.000000, "avg": 1.000000, "mean": 1.000000, "std": 0.000000 } , { "start_pos": 2040, "stop_pos": 2080,  "max": 1.000000, "min": 1.000000, "median": 1.000000, "avg": 1.000000, "mean": 1.000000, "std": 0.000000 } , { "start_pos": 2080, "stop_pos": 2120,  "max": 1.000000, "min": 1.000000, "median": 1.000000, "avg": 1.000000, "mean": 1.000000, "std": 0.000000 } , { "start_pos": 2120, "stop_pos": 2160,  "max": 1.000000, "min": 1.000000, "median": 1.000000, "avg": 1.000000, "mean": 1.000000, "std": 0.000000 } , { "start_pos": 2160, "stop_pos": 2200,  "max": 1.000000, "min": 1.000000, "median": 1.000000, "avg": 1.000000, "mean": 1.000000, "std": 0.000000 } , { "start_pos": 2200, "stop_pos": 2240,  "max": 1.000000, "min": 1.000000, "median": 1.000000, "avg": 1.000000, "mean": 1.000000, "std": 0.000000 } , { "start_pos": 2240, "stop_pos": 2280,  "max": 1.000000, "min": 1.000000, "median": 1.000000, "avg": 1.000000, "mean": 1.000000, "std": 0.000000 } , { "start_pos": 2280, "stop_pos": 2320,  "max": 1.000000, "min": 1.000000, "median": 1.000000, "avg": 1.000000, "mean": 1.000000, "std": 0.000000 } , { "start_pos": 2320, "stop_pos": 2360,  "max": 1.000000, "min": 1.000000, "median": 1.000000, "avg": 1.000000, "mean": 1.000000, "std": 0.000000 } , { "start_pos": 2360, "stop_pos": 2400,  "max": 1.000000, "min": 1.000000, "median": 1.000000, "avg": 1.000000, "mean": 1.000000, "std": 0.000000 } , { "start_pos": 2400, "stop_pos": 2440,  "max": 1.000000, "min": 1.000000, "median": 1.000000, "avg": 1.000000, "mean": 1.000000, "std": 0.000000 } , { "start_pos": 2440, "stop_pos": 2480,  "max": 1.000000, "min": 1.000000, "median": 1.000000, "avg": 1.000000, "mean": 1.000000, "std": 0.000000 } , { "start_pos": 2480, "stop_pos": 2520,  "max": 1.000000, "min": 1.000000, "median": 1.000000, "avg": 1.000000, "mean": 1.000000, "std": 0.000000 } , { "start_pos": 2520, "stop_pos": 2560,  "max": 1.000000, "min": 1.000000, "median": 1.000000, "avg": 1.000000, "mean": 1.000000, "std": 0.000000 } , { "start_pos": 2560, "stop_pos": 2600,  "max": 1.000000, "min": 1.000000, "median": 1.000000, "avg": 1.000000, "mean": 1.000000, "std": 0.000000 } , { "start_pos": 2600, "stop_pos": 2640,  "max": 1.000000, "min": 1.000000, "median": 1.000000, "avg": 1.000000, "mean": 1.000000, "std": 0.000000 } , { "start_pos": 2640, "stop_pos": 2680,  "max": 1.000000, "min": 1.000000, "median": 1.000000, "avg": 1.000000, "mean": 1.000000, "std": 0.000000 } , { "start_pos": 2680, "stop_pos": 2720,  "max": 1.000000, "min": 1.000000, "median": 1.000000, "avg": 1.000000, "mean": 1.000000, "std": 0.000000 } , { "start_pos": 2720, "stop_pos": 2760,  "max": 1.000000, "min": 1.000000, "median": 1.000000, "avg": 1.000000, "mean": 1.000000, "std": 0.000000 } , { "start_pos": 2760, "stop_pos": 2800,  "max": 1.000000, "min": 1.000000, "median": 1.000000, "avg": 1.000000, "mean": 1.000000, "std": 0.000000 } , { "start_pos": 2800, "stop_pos": 2840,  "max": 1.000000, "min": 1.000000, "median": 1.000000, "avg": 1.000000, "mean": 1.000000, "std": 0.000000 } , { "start_pos": 2840, "stop_pos": 2880,  "max": 1.000000, "min": 1.000000, "median": 1.000000, "avg": 1.000000, "mean": 1.000000, "std": 0.000000 } , { "start_pos": 2880, "stop_pos": 2920,  "max": 1.000000, "min": 1.000000, "median": 1.000000, "avg": 1.000000, "mean": 1.000000, "std": 0.000000 } , { "start_pos": 2920, "stop_pos": 2960,  "max": 1.000000, "min": 1.000000, "median": 1.000000, "avg": 1.000000, "mean": 1.000000, "std": 0.000000 } , { "start_pos": 2960, "stop_pos": 3000,  "max": 1.000000, "min": 1.000000, "median": 1.000000, "avg": 1.000000, "mean": 1.000000, "std": 0.000000 } , { "start_pos": 3000, "stop_pos": 3040,  "max": 1.000000, "min": 1.000000, "median": 1.000000, "avg": 1.000000, "mean": 1.000000, "std": 0.000000 } , { "start_pos": 3040, "stop_pos": 3080,  "max": 1.000000, "min": 1.000000, "median": 1.000000, "avg": 1.000000, "mean": 1.000000, "std": 0.000000 } , { "start_pos": 3080, "stop_pos": 3120,  "max": 1.000000, "min": 1.000000, "median": 1.000000, "avg": 1.000000, "mean": 1.000000, "std": 0.000000 } , { "start_pos": 3120, "stop_pos": 3160,  "max": 1.000000, "min": 1.000000, "median": 1.000000, "avg": 1.000000, "mean": 1.000000, "std": 0.000000 } , { "start_pos": 3160, "stop_pos": 3200,  "max": 1.000000, "min": 1.000000, "median": 1.000000, "avg": 1.000000, "mean": 1.000000, "std": 0.000000 } , { "start_pos": 3200, "stop_pos": 3240,  "max": 1.000000, "min": 1.000000, "median": 1.000000, "avg": 1.000000, "mean": 1.000000, "std": 0.000000 } , { "start_pos": 3240, "stop_pos": 3280,  "max": 1.000000, "min": 1.000000, "median": 1.000000, "avg": 1.000000, "mean": 1.000000, "std": 0.000000 } , { "start_pos": 3280, "stop_pos": 3320,  "max": 1.000000, "min": 1.000000, "median": 1.000000, "avg": 1.000000, "mean": 1.000000, "std": 0.000000 } , { "start_pos": 3320, "stop_pos": 3360,  "max": 1.000000, "min": 1.000000, "median": 1.000000, "avg": 1.000000, "mean": 1.000000, "std": 0.000000 } , { "start_pos": 3360, "stop_pos": 3400,  "max": 1.000000, "min": 1.000000, "median": 1.000000, "avg": 1.000000, "mean": 1.000000, "std": 0.000000 } , { "start_pos": 3400, "stop_pos": 3440,  "max": 1.000000, "min": 1.000000, "median": 1.000000, "avg": 1.000000, "mean": 1.000000, "std": 0.000000 } , { "start_pos": 3440, "stop_pos": 3480,  "max": 1.000000, "min": 1.000000, "median": 1.000000, "avg": 1.000000, "mean": 1.000000, "std": 0.000000 } , { "start_pos": 3480, "stop_pos": 3520,  "max": 1.000000, "min": 1.000000, "median": 1.000000, "avg": 1.000000, "mean": 1.000000, "std": 0.000000 } , { "start_pos": 3520, "stop_pos": 3560,  "max": 1.000000, "min": 1.000000, "median": 1.000000, "avg": 1.000000, "mean": 1.000000, "std": 0.000000 } , { "start_pos": 3560, "stop_pos": 3600,  "max": 1.000000, "min": 1.000000, "median": 1.000000, "avg": 1.000000, "mean": 1.000000, "std": 0.000000 } , { "start_pos": 3600, "stop_pos": 3640,  "max": 1.000000, "min": 1.000000, "median": 1.000000, "avg": 1.000000, "mean": 1.000000, "std": 0.000000 } , { "start_pos": 3640, "stop_pos": 3680,  "max": 1.000000, "min": 1.000000, "median": 1.000000, "avg": 1.000000, "mean": 1.000000, "std": 0.000000 } , { "start_pos": 3680, "stop_pos": 3720,  "max": 1.000000, "min": 1.000000, "median": 1.000000, "avg": 1.000000, "mean": 1.000000, "std": 0.000000 } , { "start_pos": 3720, "stop_pos": 3760,  "max": 1.000000, "min": 1.000000, "median": 1.000000, "avg": 1.000000, "mean": 1.000000, "std": 0.000000 } , { "start_pos": 3760, "stop_pos": 3800,  "max": 1.000000, "min": 1.000000, "median": 1.000000, "avg": 1.000000, "mean": 1.000000, "std": 0.000000 } , { "start_pos": 3800, "stop_pos": 3840,  "max": 1.000000, "min": 1.000000, "median": 1.000000, "avg": 1.000000, "mean": 1.000000, "std": 0.000000 } , { "start_pos": 3840, "stop_pos": 3880,  "max": 1.000000, "min": 1.000000, "median": 1.000000, "avg": 1.000000, "mean": 1.000000, "std": 0.000000 } , { "start_pos": 3880, "stop_pos": 3920,  "max": 1.000000, "min": 1.000000, "median": 1.000000, "avg": 1.000000, "mean": 1.000000, "std": 0.000000 } , { "start_pos": 3920, "stop_pos": 3960,  "max": 1.000000, "min": 1.000000, "median": 1.000000, "avg": 1.000000, "mean": 1.000000, "std": 0.000000 } , { "start_pos": 3960, "stop_pos": 4000,  "max": 1.000000, "min": 1.000000, "median": 1.000000, "avg": 1.000000, "mean": 1.000000, "std": 0.000000 } ], "data_mRNA": [  { "start_pos": 0, "stop_pos": 40,  "max": 24.000000, "min": 10.000000, "median": 20.000000, "avg": 18.675000, "mean": 18.675000, "std": 3.676870 } , { "start_pos": 40, "stop_pos": 80,  "max": 15.000000, "min": 8.000000, "median": 9.500000, "avg": 9.950000, "mean": 9.950000, "std": 1.829617 } , { "start_pos": 80, "stop_pos": 120,  "max": 8.000000, "min": 5.000000, "median": 6.000000, "avg": 6.200000, "mean": 6.200000, "std": 1.249000 } , { "start_pos": 120, "stop_pos": 160,  "max": 5.000000, "min": 4.000000, "median": 5.000000, "avg": 4.850000, "mean": 4.850000, "std": 0.357071 } , { "start_pos": 160, "stop_pos": 200,  "max": 4.000000, "min": 3.000000, "median": 4.000000, "avg": 3.675000, "mean": 3.675000, "std": 0.468375 } , { "start_pos": 200, "stop_pos": 240,  "max": 5.000000, "min": 3.000000, "median": 4.000000, "avg": 3.975000, "mean": 3.975000, "std": 0.611862 } , { "start_pos": 240, "stop_pos": 280,  "max": 4.000000, "min": 1.000000, "median": 3.000000, "avg": 3.025000, "mean": 3.025000, "std": 1.106515 } , { "start_pos": 280, "stop_pos": 320,  "max": 2.000000, "min": 1.000000, "median": 1.000000, "avg": 1.325000, "mean": 1.325000, "std": 0.468375 } , { "start_pos": 320, "stop_pos": 360,  "max": 2.000000, "min": 1.000000, "median": 2.000000, "avg": 1.675000, "mean": 1.675000, "std": 0.468375 } , { "start_pos": 360, "stop_pos": 400,  "max": 3.000000, "min": 1.000000, "median": 3.000000, "avg": 2.475000, "mean": 2.475000, "std": 0.631961 } , { "start_pos": 400, "stop_pos": 440,  "max": 2.000000, "min": 1.000000, "median": 1.000000, "avg": 1.050000, "mean": 1.050000, "std": 0.217945 } , { "start_pos": 440, "stop_pos": 480,  "max": 4.000000, "min": 3.000000, "median": 3.000000, "avg": 3.025000, "mean": 3.025000, "std": 0.156125 } , { "start_pos": 480, "stop_pos": 520,  "max": 3.000000, "min": 2.000000, "median": 3.000000, "avg": 2.525000, "mean": 2.525000, "std": 0.499375 } , { "start_pos": 520, "stop_pos": 560,  "max": 2.000000, "min": 2.000000, "median": 2.000000, "avg": 2.000000, "mean": 2.000000, "std": 0.000000 } , { "start_pos": 560, "stop_pos": 600,  "max": 2.000000, "min": 1.000000, "median": 1.000000, "avg": 1.325000, "mean": 1.325000, "std": 0.468375 } , { "start_pos": 600, "stop_pos": 640,  "max": 2.000000, "min": 0.000000, "median": 0.000000, "avg": 0.400000, "mean": 0.400000, "std": 0.734847 } , { "start_pos": 640, "stop_pos": 680,  "max": 2.000000, "min": 1.000000, "median": 1.000000, "avg": 1.225000, "mean": 1.225000, "std": 0.417582 } , { "start_pos": 680, "stop_pos": 720,  "max": 2.000000, "min": 0.000000, "median": 0.000000, "avg": 0.575000, "mean": 0.575000, "std": 0.802730 } , { "start_pos": 720, "stop_pos": 760,  "max": 1.000000, "min": 0.000000, "median": 0.000000, "avg": 0.050000, "mean": 0.050000, "std": 0.217945 } , { "start_pos": 760, "stop_pos": 800,  "max": 3.000000, "min": 0.000000, "median": 2.000000, "avg": 2.200000, "mean": 2.200000, "std": 0.556776 } , { "start_pos": 800, "stop_pos": 840,  "max": 3.000000, "min": 2.000000, "median": 3.000000, "avg": 2.650000, "mean": 2.650000, "std": 0.476970 } , { "start_pos": 840, "stop_pos": 880,  "max": 4.000000, "min": 1.000000, "median": 3.000000, "avg": 2.750000, "mean": 2.750000, "std": 0.798436 } , { "start_pos": 880, "stop_pos": 920,  "max": 3.000000, "min": 1.000000, "median": 1.000000, "avg": 1.400000, "mean": 1.400000, "std": 0.583095 } , { "start_pos": 920, "stop_pos": 960,  "max": 2.000000, "min": 1.000000, "median": 1.000000, "avg": 1.425000, "mean": 1.425000, "std": 0.494343 } , { "start_pos": 960, "stop_pos": 1000,  "max": 2.000000, "min": 1.000000, "median": 1.000000, "avg": 1.275000, "mean": 1.275000, "std": 0.446514 } , { "start_pos": 1000, "stop_pos": 1040,  "max": 4.000000, "min": 2.000000, "median": 2.000000, "avg": 2.450000, "mean": 2.450000, "std": 0.630476 } , { "start_pos": 1040, "stop_pos": 1080,  "max": 3.000000, "min": 2.000000, "median": 2.000000, "avg": 2.325000, "mean": 2.325000, "std": 0.468375 } , { "start_pos": 1080, "stop_pos": 1120,  "max": 2.000000, "min": 1.000000, "median": 1.000000, "avg": 1.475000, "mean": 1.475000, "std": 0.499375 } , { "start_pos": 1120, "stop_pos": 1160,  "max": 2.000000, "min": 0.000000, "median": 1.000000, "avg": 1.325000, "mean": 1.325000, "std": 0.519013 } , { "start_pos": 1160, "stop_pos": 1200,  "max": 2.000000, "min": 0.000000, "median": 1.000000, "avg": 1.125000, "mean": 1.125000, "std": 0.509289 } , { "start_pos": 1200, "stop_pos": 1240,  "max": 1.000000, "min": 0.000000, "median": 0.000000, "avg": 0.250000, "mean": 0.250000, "std": 0.433013 } , { "start_pos": 1240, "stop_pos": 1280,  "max": 1.000000, "min": 0.000000, "median": 0.000000, "avg": 0.375000, "mean": 0.375000, "std": 0.484123 } , { "start_pos": 1280, "stop_pos": 1320,  "max": 2.000000, "min": 0.000000, "median": 0.000000, "avg": 0.525000, "mean": 0.525000, "std": 0.741198 } , { "start_pos": 1320, "stop_pos": 1360,  "max": 4.000000, "min": 1.000000, "median": 2.000000, "avg": 2.000000, "mean": 2.000000, "std": 0.547723 } , { "start_pos": 1360, "stop_pos": 1400,  "max": 4.000000, "min": 3.000000, "median": 4.000000, "avg": 3.575000, "mean": 3.575000, "std": 0.494343 } , { "start_pos": 1400, "stop_pos": 1440,  "max": 5.000000, "min": 3.000000, "median": 4.000000, "avg": 4.100000, "mean": 4.100000, "std": 0.800000 } , { "start_pos": 1440, "stop_pos": 1480,  "max": 5.000000, "min": 3.000000, "median": 4.000000, "avg": 4.275000, "mean": 4.275000, "std": 0.499375 } , { "start_pos": 1480, "stop_pos": 1520,  "max": 4.000000, "min": 1.000000, "median": 2.000000, "avg": 2.550000, "mean": 2.550000, "std": 0.893029 } , { "start_pos": 1520, "stop_pos": 1560,  "max": 2.000000, "min": 2.000000, "median": 2.000000, "avg": 2.000000, "mean": 2.000000, "std": 0.000000 } , { "start_pos": 1560, "stop_pos": 1600,  "max": 2.000000, "min": 0.000000, "median": 1.000000, "avg": 0.825000, "mean": 0.825000, "std": 0.494343 } , { "start_pos": 1600, "stop_pos": 1640,  "max": 2.000000, "min": 1.000000, "median": 2.000000, "avg": 1.700000, "mean": 1.700000, "std": 0.458258 } , { "start_pos": 1640, "stop_pos": 1680,  "max": 2.000000, "min": 2.000000, "median": 2.000000, "avg": 2.000000, "mean": 2.000000, "std": 0.000000 } , { "start_pos": 1680, "stop_pos": 1720,  "max": 2.000000, "min": 0.000000, "median": 1.000000, "avg": 1.000000, "mean": 1.000000, "std": 0.974679 } , { "start_pos": 1720, "stop_pos": 1760,  "max": 2.000000, "min": 0.000000, "median": 1.000000, "avg": 1.100000, "mean": 1.100000, "std": 0.583095 } , { "start_pos": 1760, "stop_pos": 1800,  "max": 5.000000, "min": 1.000000, "median": 2.000000, "avg": 2.475000, "mean": 2.475000, "std": 1.117754 } , { "start_pos": 1800, "stop_pos": 1840,  "max": 4.000000, "min": 3.000000, "median": 3.000000, "avg": 3.400000, "mean": 3.400000, "std": 0.489898 } , { "start_pos": 1840, "stop_pos": 1880,  "max": 4.000000, "min": 3.000000, "median": 3.000000, "avg": 3.425000, "mean": 3.425000, "std": 0.494343 } , { "start_pos": 1880, "stop_pos": 1920,  "max": 3.000000, "min": 3.000000, "median": 3.000000, "avg": 3.000000, "mean": 3.000000, "std": 0.000000 } , { "start_pos": 1920, "stop_pos": 1960,  "max": 4.000000, "min": 3.000000, "median": 3.000000, "avg": 3.325000, "mean": 3.325000, "std": 0.468375 } , { "start_pos": 1960, "stop_pos": 2000,  "max": 4.000000, "min": 2.000000, "median": 2.000000, "avg": 2.450000, "mean": 2.450000, "std": 0.589491 } , { "start_pos": 2000, "stop_pos": 2040,  "max": 2.000000, "min": 0.000000, "median": 1.000000, "avg": 1.275000, "mean": 1.275000, "std": 0.631961 } , { "start_pos": 2040, "stop_pos": 2080,  "max": 0.000000, "min": 0.000000, "median": 0.000000, "avg": 0.000000, "mean": 0.000000, "std": 0.000000 } , { "start_pos": 2080, "stop_pos": 2120,  "max": 1.000000, "min": 0.000000, "median": 1.000000, "avg": 0.550000, "mean": 0.550000, "std": 0.497494 } , { "start_pos": 2120, "stop_pos": 2160,  "max": 1.000000, "min": 1.000000, "median": 1.000000, "avg": 1.000000, "mean": 1.000000, "std": 0.000000 } , { "start_pos": 2160, "stop_pos": 2200,  "max": 1.000000, "min": 0.000000, "median": 0.000000, "avg": 0.375000, "mean": 0.375000, "std": 0.484123 } , { "start_pos": 2200, "stop_pos": 2240,  "max": 1.000000, "min": 0.000000, "median": 1.000000, "avg": 0.600000, "mean": 0.600000, "std": 0.489898 } , { "start_pos": 2240, "stop_pos": 2280,  "max": 1.000000, "min": 0.000000, "median": 0.000000, "avg": 0.325000, "mean": 0.325000, "std": 0.468375 } , { "start_pos": 2280, "stop_pos": 2320,  "max": 2.000000, "min": 0.000000, "median": 1.000000, "avg": 0.625000, "mean": 0.625000, "std": 0.619980 } , { "start_pos": 2320, "stop_pos": 2360,  "max": 1.000000, "min": 1.000000, "median": 1.000000, "avg": 1.000000, "mean": 1.000000, "std": 0.000000 } , { "start_pos": 2360, "stop_pos": 2400,  "max": 1.000000, "min": 1.000000, "median": 1.000000, "avg": 1.000000, "mean": 1.000000, "std": 0.000000 } , { "start_pos": 2400, "stop_pos": 2440,  "max": 2.000000, "min": 1.000000, "median": 2.000000, "avg": 1.700000, "mean": 1.700000, "std": 0.458258 } , { "start_pos": 2440, "stop_pos": 2480,  "max": 2.000000, "min": 1.000000, "median": 1.000000, "avg": 1.450000, "mean": 1.450000, "std": 0.497494 } , { "start_pos": 2480, "stop_pos": 2520,  "max": 2.000000, "min": 1.000000, "median": 1.000000, "avg": 1.475000, "mean": 1.475000, "std": 0.499375 } , { "start_pos": 2520, "stop_pos": 2560,  "max": 2.000000, "min": 0.000000, "median": 1.000000, "avg": 1.175000, "mean": 1.175000, "std": 0.542563 } , { "start_pos": 2560, "stop_pos": 2600,  "max": 2.000000, "min": 1.000000, "median": 1.000000, "avg": 1.025000, "mean": 1.025000, "std": 0.156125 } , { "start_pos": 2600, "stop_pos": 2640,  "max": 2.000000, "min": 1.000000, "median": 1.000000, "avg": 1.300000, "mean": 1.300000, "std": 0.458258 } , { "start_pos": 2640, "stop_pos": 2680,  "max": 1.000000, "min": 0.000000, "median": 0.000000, "avg": 0.400000, "mean": 0.400000, "std": 0.489898 } , { "start_pos": 2680, "stop_pos": 2720,  "max": 0.000000, "min": 0.000000, "median": 0.000000, "avg": 0.000000, "mean": 0.000000, "std": 0.000000 } , { "start_pos": 2720, "stop_pos": 2760,  "max": 0.000000, "min": 0.000000, "median": 0.000000, "avg": 0.000000, "mean": 0.000000, "std": 0.000000 } , { "start_pos": 2760, "stop_pos": 2800,  "max": 1.000000, "min": 0.000000, "median": 1.000000, "avg": 0.825000, "mean": 0.825000, "std": 0.379967 } , { "start_pos": 2800, "stop_pos": 2840,  "max": 5.000000, "min": 1.000000, "median": 3.000000, "avg": 3.300000, "mean": 3.300000, "std": 1.630951 } , { "start_pos": 2840, "stop_pos": 2880,  "max": 5.000000, "min": 3.000000, "median": 4.000000, "avg": 4.100000, "mean": 4.100000, "std": 0.538516 } , { "start_pos": 2880, "stop_pos": 2920,  "max": 5.000000, "min": 2.000000, "median": 5.000000, "avg": 4.250000, "mean": 4.250000, "std": 1.042833 } , { "start_pos": 2920, "stop_pos": 2960,  "max": 3.000000, "min": 1.000000, "median": 2.000000, "avg": 1.850000, "mean": 1.850000, "std": 0.526783 } , { "start_pos": 2960, "stop_pos": 3000,  "max": 1.000000, "min": 0.000000, "median": 1.000000, "avg": 0.600000, "mean": 0.600000, "std": 0.489898 } , { "start_pos": 3000, "stop_pos": 3040,  "max": 0.000000, "min": 0.000000, "median": 0.000000, "avg": 0.000000, "mean": 0.000000, "std": 0.000000 } , { "start_pos": 3040, "stop_pos": 3080,  "max": 2.000000, "min": 0.000000, "median": 1.000000, "avg": 1.125000, "mean": 1.125000, "std": 0.677772 } , { "start_pos": 3080, "stop_pos": 3120,  "max": 2.000000, "min": 0.000000, "median": 1.000000, "avg": 1.075000, "mean": 1.075000, "std": 0.685109 } , { "start_pos": 3120, "stop_pos": 3160,  "max": 0.000000, "min": 0.000000, "median": 0.000000, "avg": 0.000000, "mean": 0.000000, "std": 0.000000 } , { "start_pos": 3160, "stop_pos": 3200,  "max": 2.000000, "min": 0.000000, "median": 1.000000, "avg": 0.950000, "mean": 0.950000, "std": 0.705337 } , { "start_pos": 3200, "stop_pos": 3240,  "max": 1.000000, "min": 1.000000, "median": 1.000000, "avg": 1.000000, "mean": 1.000000, "std": 0.000000 } , { "start_pos": 3240, "stop_pos": 3280,  "max": 1.000000, "min": 1.000000, "median": 1.000000, "avg": 1.000000, "mean": 1.000000, "std": 0.000000 } , { "start_pos": 3280, "stop_pos": 3320,  "max": 1.000000, "min": 0.000000, "median": 0.000000, "avg": 0.250000, "mean": 0.250000, "std": 0.433013 } , { "start_pos": 3320, "stop_pos": 3360,  "max": 0.000000, "min": 0.000000, "median": 0.000000, "avg": 0.000000, "mean": 0.000000, "std": 0.000000 } , { "start_pos": 3360, "stop_pos": 3400,  "max": 1.000000, "min": 0.000000, "median": 0.000000, "avg": 0.125000, "mean": 0.125000, "std": 0.330719 } , { "start_pos": 3400, "stop_pos": 3440,  "max": 1.000000, "min": 0.000000, "median": 0.000000, "avg": 0.425000, "mean": 0.425000, "std": 0.494343 } , { "start_pos": 3440, "stop_pos": 3480,  "max": 2.000000, "min": 0.000000, "median": 2.000000, "avg": 1.350000, "mean": 1.350000, "std": 0.792149 } , { "start_pos": 3480, "stop_pos": 3520,  "max": 4.000000, "min": 2.000000, "median": 3.000000, "avg": 3.300000, "mean": 3.300000, "std": 0.600000 } , { "start_pos": 3520, "stop_pos": 3560,  "max": 6.000000, "min": 3.000000, "median": 6.000000, "avg": 4.975000, "mean": 4.975000, "std": 1.172337 } , { "start_pos": 3560, "stop_pos": 3600,  "max": 6.000000, "min": 2.000000, "median": 3.000000, "avg": 3.225000, "mean": 3.225000, "std": 1.274510 } , { "start_pos": 3600, "stop_pos": 3640,  "max": 3.000000, "min": 1.000000, "median": 1.500000, "avg": 1.775000, "mean": 1.775000, "std": 0.851102 } , { "start_pos": 3640, "stop_pos": 3680,  "max": 1.000000, "min": 0.000000, "median": 0.000000, "avg": 0.050000, "mean": 0.050000, "std": 0.217945 } , { "start_pos": 3680, "stop_pos": 3720,  "max": 2.000000, "min": 0.000000, "median": 1.000000, "avg": 0.875000, "mean": 0.875000, "std": 0.639824 } , { "start_pos": 3720, "stop_pos": 3760,  "max": 2.000000, "min": 2.000000, "median": 2.000000, "avg": 2.000000, "mean": 2.000000, "std": 0.000000 } , { "start_pos": 3760, "stop_pos": 3800,  "max": 3.000000, "min": 1.000000, "median": 2.000000, "avg": 1.725000, "mean": 1.725000, "std": 0.631961 } , { "start_pos": 3800, "stop_pos": 3840,  "max": 1.000000, "min": 0.000000, "median": 0.000000, "avg": 0.100000, "mean": 0.100000, "std": 0.300000 } , { "start_pos": 3840, "stop_pos": 3880,  "max": 1.000000, "min": 0.000000, "median": 0.000000, "avg": 0.200000, "mean": 0.200000, "std": 0.400000 } , { "start_pos": 3880, "stop_pos": 3920,  "max": 2.000000, "min": 1.000000, "median": 1.000000, "avg": 1.475000, "mean": 1.475000, "std": 0.499375 } , { "start_pos": 3920, "stop_pos": 3960,  "max": 1.000000, "min": 0.000000, "median": 0.000000, "avg": 0.075000, "mean": 0.075000, "std": 0.263391 } , { "start_pos": 3960, "stop_pos": 4000,  "max": 1.000000, "min": 0.000000, "median": 0.000000, "avg": 0.300000, "mean": 0.300000, "std": 0.458258 } ], "data_protein": [  { "start_pos": 0, "stop_pos": 40,  "max": 153.000000, "min": 60.000000, "median": 93.000000, "avg": 97.325000, "mean": 97.325000, "std": 30.436317 } , { "start_pos": 40, "stop_pos": 80,  "max": 185.000000, "min": 154.000000, "median": 177.500000, "avg": 173.975000, "mean": 173.975000, "std": 8.650108 } , { "start_pos": 80, "stop_pos": 120,  "max": 191.000000, "min": 176.000000, "median": 181.000000, "avg": 181.825000, "mean": 181.825000, "std": 3.760901 } , { "start_pos": 120, "stop_pos": 160,  "max": 183.000000, "min": 169.000000, "median": 176.000000, "avg": 175.525000, "mean": 175.525000, "std": 3.936925 } , { "start_pos": 160, "stop_pos": 200,  "max": 172.000000, "min": 146.000000, "median": 156.500000, "avg": 157.200000, "mean": 157.200000, "std": 6.950540 } , { "start_pos": 200, "stop_pos": 240,  "max": 147.000000, "min": 133.000000, "median": 142.000000, "avg": 140.550000, "mean": 140.550000, "std": 4.641928 } , { "start_pos": 240, "stop_pos": 280,  "max": 139.000000, "min": 130.000000, "median": 133.000000, "avg": 133.500000, "mean": 133.500000, "std": 2.280351 } , { "start_pos": 280, "stop_pos": 320,  "max": 130.000000, "min": 101.000000, "median": 112.500000, "avg": 112.525000, "mean": 112.525000, "std": 8.139372 } , { "start_pos": 320, "stop_pos": 360,  "max": 101.000000, "min": 83.000000, "median": 87.500000, "avg": 89.975000, "mean": 89.975000, "std": 6.218872 } , { "start_pos": 360, "stop_pos": 400,  "max": 83.000000, "min": 72.000000, "median": 81.000000, "avg": 80.025000, "mean": 80.025000, "std": 2.919653 } , { "start_pos": 400, "stop_pos": 440,  "max": 71.000000, "min": 59.000000, "median": 65.000000, "avg": 65.125000, "mean": 65.125000, "std": 2.758510 } , { "start_pos": 440, "stop_pos": 480,  "max": 72.000000, "min": 57.000000, "median": 66.000000, "avg": 64.700000, "mean": 64.700000, "std": 4.675468 } , { "start_pos": 480, "stop_pos": 520,  "max": 83.000000, "min": 70.000000, "median": 76.000000, "avg": 75.825000, "mean": 75.825000, "std": 3.590874 } , { "start_pos": 520, "stop_pos": 560,  "max": 72.000000, "min": 68.000000, "median": 70.000000, "avg": 69.975000, "mean": 69.975000, "std": 1.274510 } , { "start_pos": 560, "stop_pos": 600,  "max": 69.000000, "min": 55.000000, "median": 58.000000, "avg": 58.900000, "mean": 58.900000, "std": 3.534119 } , { "start_pos": 600, "stop_pos": 640,  "max": 55.000000, "min": 45.000000, "median": 50.000000, "avg": 50.250000, "mean": 50.250000, "std": 3.329790 } , { "start_pos": 640, "stop_pos": 680,  "max": 42.000000, "min": 30.000000, "median": 32.000000, "avg": 33.850000, "mean": 33.850000, "std": 3.460852 } , { "start_pos": 680, "stop_pos": 720,  "max": 33.000000, "min": 30.000000, "median": 31.000000, "avg": 31.425000, "mean": 31.425000, "std": 1.092875 } , { "start_pos": 720, "stop_pos": 760,  "max": 30.000000, "min": 19.000000, "median": 25.000000, "avg": 25.050000, "mean": 25.050000, "std": 3.846752 } , { "start_pos": 760, "stop_pos": 800,  "max": 25.000000, "min": 17.000000, "median": 20.000000, "avg": 20.875000, "mean": 20.875000, "std": 2.628569 } , { "start_pos": 800, "stop_pos": 840,  "max": 44.000000, "min": 25.000000, "median": 29.500000, "avg": 33.000000, "mean": 33.000000, "std": 6.399219 } , { "start_pos": 840, "stop_pos": 880,  "max": 48.000000, "min": 42.000000, "median": 44.000000, "avg": 44.425000, "mean": 44.425000, "std": 1.531135 } , { "start_pos": 880, "stop_pos": 920,  "max": 47.000000, "min": 39.000000, "median": 42.000000, "avg": 42.350000, "mean": 42.350000, "std": 1.956400 } , { "start_pos": 920, "stop_pos": 960,  "max": 42.000000, "min": 34.000000, "median": 38.000000, "avg": 37.800000, "mean": 37.800000, "std": 2.570992 } , { "start_pos": 960, "stop_pos": 1000,  "max": 42.000000, "min": 30.000000, "median": 37.000000, "avg": 36.475000, "mean": 36.475000, "std": 2.974790 } , { "start_pos": 1000, "stop_pos": 1040,  "max": 48.000000, "min": 29.000000, "median": 36.000000, "avg": 35.725000, "mean": 35.725000, "std": 4.549657 } , { "start_pos": 1040, "stop_pos": 1080,  "max": 52.000000, "min": 41.000000, "median": 45.000000, "avg": 46.100000, "mean": 46.100000, "std": 3.706751 } , { "start_pos": 1080, "stop_pos": 1120,  "max": 44.000000, "min": 37.000000, "median": 39.000000, "avg": 39.600000, "mean": 39.600000, "std": 2.009975 } , { "start_pos": 1120, "stop_pos": 1160,  "max": 44.000000, "min": 39.000000, "median": 41.000000, "avg": 41.300000, "mean": 41.300000, "std": 1.568439 } , { "start_pos": 1160, "stop_pos": 1200,  "max": 41.000000, "min": 31.000000, "median": 33.000000, "avg": 35.000000, "mean": 35.000000, "std": 3.405877 } , { "start_pos": 1200, "stop_pos": 1240,  "max": 33.000000, "min": 28.000000, "median": 31.000000, "avg": 31.300000, "mean": 31.300000, "std": 1.187434 } , { "start_pos": 1240, "stop_pos": 1280,  "max": 28.000000, "min": 22.000000, "median": 27.000000, "avg": 25.450000, "mean": 25.450000, "std": 2.235509 } , { "start_pos": 1280, "stop_pos": 1320,  "max": 22.000000, "min": 15.000000, "median": 17.000000, "avg": 17.800000, "mean": 17.800000, "std": 2.238303 } , { "start_pos": 1320, "stop_pos": 1360,  "max": 23.000000, "min": 17.000000, "median": 20.000000, "avg": 19.950000, "mean": 19.950000, "std": 1.843231 } , { "start_pos": 1360, "stop_pos": 1400,  "max": 41.000000, "min": 23.000000, "median": 33.000000, "avg": 32.825000, "mean": 32.825000, "std": 4.700465 } , { "start_pos": 1400, "stop_pos": 1440,  "max": 52.000000, "min": 39.000000, "median": 48.500000, "avg": 45.750000, "mean": 45.750000, "std": 4.768385 } , { "start_pos": 1440, "stop_pos": 1480,  "max": 84.000000, "min": 49.000000, "median": 62.000000, "avg": 65.000000, "mean": 65.000000, "std": 11.137774 } , { "start_pos": 1480, "stop_pos": 1520,  "max": 78.000000, "min": 71.000000, "median": 75.000000, "avg": 74.950000, "mean": 74.950000, "std": 2.120731 } , { "start_pos": 1520, "stop_pos": 1560,  "max": 74.000000, "min": 62.000000, "median": 69.000000, "avg": 68.225000, "mean": 68.225000, "std": 2.893851 } , { "start_pos": 1560, "stop_pos": 1600,  "max": 62.000000, "min": 54.000000, "median": 59.000000, "avg": 59.250000, "mean": 59.250000, "std": 2.021757 } , { "start_pos": 1600, "stop_pos": 1640,  "max": 58.000000, "min": 50.000000, "median": 55.000000, "avg": 54.600000, "mean": 54.600000, "std": 1.959592 } , { "start_pos": 1640, "stop_pos": 1680,  "max": 61.000000, "min": 51.000000, "median": 54.500000, "avg": 55.425000, "mean": 55.425000, "std": 2.625714 } , { "start_pos": 1680, "stop_pos": 1720,  "max": 61.000000, "min": 47.000000, "median": 58.000000, "avg": 55.400000, "mean": 55.400000, "std": 4.662617 } , { "start_pos": 1720, "stop_pos": 1760,  "max": 47.000000, "min": 32.000000, "median": 39.500000, "avg": 39.800000, "mean": 39.800000, "std": 4.296510 } , { "start_pos": 1760, "stop_pos": 1800,  "max": 42.000000, "min": 28.000000, "median": 33.000000, "avg": 32.875000, "mean": 32.875000, "std": 2.917083 } , { "start_pos": 1800, "stop_pos": 1840,  "max": 66.000000, "min": 43.000000, "median": 51.000000, "avg": 53.850000, "mean": 53.850000, "std": 8.187032 } , { "start_pos": 1840, "stop_pos": 1880,  "max": 87.000000, "min": 66.000000, "median": 75.500000, "avg": 76.375000, "mean": 76.375000, "std": 6.988160 } , { "start_pos": 1880, "stop_pos": 1920,  "max": 99.000000, "min": 87.000000, "median": 93.000000, "avg": 92.850000, "mean": 92.850000, "std": 3.094754 } , { "start_pos": 1920, "stop_pos": 1960,  "max": 101.000000, "min": 82.000000, "median": 96.000000, "avg": 93.600000, "mean": 93.600000, "std": 5.713143 } , { "start_pos": 1960, "stop_pos": 2000,  "max": 95.000000, "min": 79.000000, "median": 86.000000, "avg": 87.650000, "mean": 87.650000, "std": 5.742604 } , { "start_pos": 2000, "stop_pos": 2040,  "max": 80.000000, "min": 64.000000, "median": 75.000000, "avg": 73.300000, "mean": 73.300000, "std": 5.469004 } , { "start_pos": 2040, "stop_pos": 2080,  "max": 63.000000, "min": 46.000000, "median": 54.000000, "avg": 52.975000, "mean": 52.975000, "std": 4.671657 } , { "start_pos": 2080, "stop_pos": 2120,  "max": 45.000000, "min": 25.000000, "median": 33.500000, "avg": 33.775000, "mean": 33.775000, "std": 5.926582 } , { "start_pos": 2120, "stop_pos": 2160,  "max": 33.000000, "min": 27.000000, "median": 31.000000, "avg": 30.075000, "mean": 30.075000, "std": 1.835586 } , { "start_pos": 2160, "stop_pos": 2200,  "max": 32.000000, "min": 23.000000, "median": 31.000000, "avg": 28.925000, "mean": 28.925000, "std": 3.416047 } , { "start_pos": 2200, "stop_pos": 2240,  "max": 25.000000, "min": 22.000000, "median": 22.000000, "avg": 23.050000, "mean": 23.050000, "std": 1.203121 } , { "start_pos": 2240, "stop_pos": 2280,  "max": 23.000000, "min": 16.000000, "median": 20.000000, "avg": 19.525000, "mean": 19.525000, "std": 2.355711 } , { "start_pos": 2280, "stop_pos": 2320,  "max": 16.000000, "min": 8.000000, "median": 9.500000, "avg": 10.350000, "mean": 10.350000, "std": 2.286373 } , { "start_pos": 2320, "stop_pos": 2360,  "max": 14.000000, "min": 11.000000, "median": 13.000000, "avg": 12.875000, "mean": 12.875000, "std": 0.979477 } , { "start_pos": 2360, "stop_pos": 2400,  "max": 18.000000, "min": 13.000000, "median": 16.000000, "avg": 16.100000, "mean": 16.100000, "std": 1.577973 } , { "start_pos": 2400, "stop_pos": 2440,  "max": 23.000000, "min": 16.000000, "median": 19.000000, "avg": 19.200000, "mean": 19.200000, "std": 1.886796 } , { "start_pos": 2440, "stop_pos": 2480,  "max": 26.000000, "min": 19.000000, "median": 23.000000, "avg": 22.625000, "mean": 22.625000, "std": 2.081916 } , { "start_pos": 2480, "stop_pos": 2520,  "max": 31.000000, "min": 24.000000, "median": 28.000000, "avg": 27.475000, "mean": 27.475000, "std": 1.688009 } , { "start_pos": 2520, "stop_pos": 2560,  "max": 29.000000, "min": 27.000000, "median": 28.000000, "avg": 27.950000, "mean": 27.950000, "std": 0.497494 } , { "start_pos": 2560, "stop_pos": 2600,  "max": 32.000000, "min": 25.000000, "median": 30.000000, "avg": 29.050000, "mean": 29.050000, "std": 2.048780 } , { "start_pos": 2600, "stop_pos": 2640,  "max": 30.000000, "min": 26.000000, "median": 28.000000, "avg": 28.075000, "mean": 28.075000, "std": 1.081376 } , { "start_pos": 2640, "stop_pos": 2680,  "max": 30.000000, "min": 23.000000, "median": 27.000000, "avg": 26.725000, "mean": 26.725000, "std": 1.627690 } , { "start_pos": 2680, "stop_pos": 2720,  "max": 23.000000, "min": 17.000000, "median": 20.000000, "avg": 20.000000, "mean": 20.000000, "std": 1.483240 } , { "start_pos": 2720, "stop_pos": 2760,  "max": 17.000000, "min": 13.000000, "median": 13.000000, "avg": 14.000000, "mean": 14.000000, "std": 1.549193 } , { "start_pos": 2760, "stop_pos": 2800,  "max": 18.000000, "min": 11.000000, "median": 13.000000, "avg": 13.750000, "mean": 13.750000, "std": 2.288558 } , { "start_pos": 2800, "stop_pos": 2840,  "max": 36.000000, "min": 18.000000, "median": 24.500000, "avg": 25.700000, "mean": 25.700000, "std": 5.662155 } , { "start_pos": 2840, "stop_pos": 2880,  "max": 56.000000, "min": 36.000000, "median": 44.000000, "avg": 45.125000, "mean": 45.125000, "std": 5.399942 } , { "start_pos": 2880, "stop_pos": 2920,  "max": 84.000000, "min": 56.000000, "median": 76.000000, "avg": 73.325000, "mean": 73.325000, "std": 8.226140 } , { "start_pos": 2920, "stop_pos": 2960,  "max": 89.000000, "min": 81.000000, "median": 84.000000, "avg": 84.350000, "mean": 84.350000, "std": 2.208506 } , { "start_pos": 2960, "stop_pos": 3000,  "max": 82.000000, "min": 59.000000, "median": 70.000000, "avg": 70.150000, "mean": 70.150000, "std": 5.807538 } , { "start_pos": 3000, "stop_pos": 3040,  "max": 59.000000, "min": 45.000000, "median": 50.500000, "avg": 51.675000, "mean": 51.675000, "std": 4.185615 } , { "start_pos": 3040, "stop_pos": 3080,  "max": 45.000000, "min": 38.000000, "median": 41.000000, "avg": 40.550000, "mean": 40.550000, "std": 1.935846 } , { "start_pos": 3080, "stop_pos": 3120,  "max": 48.000000, "min": 37.000000, "median": 45.000000, "avg": 43.825000, "mean": 43.825000, "std": 3.032223 } , { "start_pos": 3120, "stop_pos": 3160,  "max": 37.000000, "min": 29.000000, "median": 32.500000, "avg": 32.550000, "mean": 32.550000, "std": 2.048780 } , { "start_pos": 3160, "stop_pos": 3200,  "max": 29.000000, "min": 24.000000, "median": 27.000000, "avg": 26.750000, "mean": 26.750000, "std": 1.198958 } , { "start_pos": 3200, "stop_pos": 3240,  "max": 26.000000, "min": 20.000000, "median": 22.000000, "avg": 22.425000, "mean": 22.425000, "std": 1.626153 } , { "start_pos": 3240, "stop_pos": 3280,  "max": 29.000000, "min": 24.000000, "median": 27.000000, "avg": 26.475000, "mean": 26.475000, "std": 1.483029 } , { "start_pos": 3280, "stop_pos": 3320,  "max": 30.000000, "min": 25.000000, "median": 28.000000, "avg": 27.800000, "mean": 27.800000, "std": 1.077033 } , { "start_pos": 3320, "stop_pos": 3360,  "max": 24.000000, "min": 15.000000, "median": 20.000000, "avg": 19.300000, "mean": 19.300000, "std": 2.776689 } , { "start_pos": 3360, "stop_pos": 3400,  "max": 15.000000, "min": 10.000000, "median": 13.000000, "avg": 12.550000, "mean": 12.550000, "std": 1.611676 } , { "start_pos": 3400, "stop_pos": 3440,  "max": 10.000000, "min": 8.000000, "median": 10.000000, "avg": 9.550000, "mean": 9.550000, "std": 0.739932 } , { "start_pos": 3440, "stop_pos": 3480,  "max": 20.000000, "min": 6.000000, "median": 8.000000, "avg": 9.925000, "mean": 9.925000, "std": 3.408720 } , { "start_pos": 3480, "stop_pos": 3520,  "max": 43.000000, "min": 22.000000, "median": 31.500000, "avg": 32.700000, "mean": 32.700000, "std": 5.818935 } , { "start_pos": 3520, "stop_pos": 3560,  "max": 78.000000, "min": 44.000000, "median": 61.500000, "avg": 60.950000, "mean": 60.950000, "std": 8.393301 } , { "start_pos": 3560, "stop_pos": 3600,  "max": 102.000000, "min": 78.000000, "median": 96.500000, "avg": 95.125000, "mean": 95.125000, "std": 5.311250 } , { "start_pos": 3600, "stop_pos": 3640,  "max": 93.000000, "min": 81.000000, "median": 89.000000, "avg": 88.650000, "mean": 88.650000, "std": 2.564664 } , { "start_pos": 3640, "stop_pos": 3680,  "max": 80.000000, "min": 57.000000, "median": 66.500000, "avg": 67.100000, "mean": 67.100000, "std": 6.733498 } , { "start_pos": 3680, "stop_pos": 3720,  "max": 57.000000, "min": 46.000000, "median": 50.500000, "avg": 51.025000, "mean": 51.025000, "std": 3.205367 } , { "start_pos": 3720, "stop_pos": 3760,  "max": 49.000000, "min": 47.000000, "median": 48.000000, "avg": 48.200000, "mean": 48.200000, "std": 0.748331 } , { "start_pos": 3760, "stop_pos": 3800,  "max": 65.000000, "min": 48.000000, "median": 62.000000, "avg": 59.675000, "mean": 59.675000, "std": 4.906055 } , { "start_pos": 3800, "stop_pos": 3840,  "max": 65.000000, "min": 47.000000, "median": 59.000000, "avg": 57.700000, "mean": 57.700000, "std": 5.883026 } , { "start_pos": 3840, "stop_pos": 3880,  "max": 46.000000, "min": 31.000000, "median": 38.000000, "avg": 38.275000, "mean": 38.275000, "std": 4.706312 } , { "start_pos": 3880, "stop_pos": 3920,  "max": 34.000000, "min": 30.000000, "median": 33.000000, "avg": 32.750000, "mean": 32.750000, "std": 0.993730 } , { "start_pos": 3920, "stop_pos": 3960,  "max": 32.000000, "min": 21.000000, "median": 26.500000, "avg": 26.375000, "mean": 26.375000, "std": 3.381475 } , { "start_pos": 3960, "stop_pos": 4000,  "max": 21.000000, "min": 14.000000, "median": 18.000000, "avg": 17.375000, "mean": 17.375000, "std": 2.556242 } ] }
